Workbook

Sheet Total Score
B2: Final Score (out of 100)
A3: # | B3: Company | C3: Growth Score | D3: Return Score | E3: Leverage Score | F3: Valuation Score | G3: Total Score = Growth Score * 0.25 + Return Score * 0.25 + Leverage Score * 0.25 + Valuation Score * 0.25
B4: LTIMINDTREE LTD | C4: ='Percentile Ranking'!C120/3+'Percentile Ranking'!D120/3+'Percentile Ranking'!E120/3 -> 0.856 | D4: ='Percentile Ranking'!F120*0.25+'Percentile Ranking'!G120*0.25+'Percentile Ranking'!H120*0.25+'Percentile Ranking'!I120*0.25 -> 0.901 | E4: ='Percentile Ranking'!J120/3 + 'Percentile Ranking'!K120/3 + 'Percentile Ranking'!L120/3 -> 0.70333333 | F4: ='Percentile Ranking'!M120/3 + 'Percentile Ranking'!N120/3 + 'Percentile Ranking'!O120/3 -> 0.67833333 | G4: =C4 * 0.25 + D4 * 0.25 + E4 * 0.25 + F4 * 0.25 -> 0.78466667
B5: NATIONAL ALUMINIUM COMPANY LTD | C5: ='Percentile Ranking'!C134/3+'Percentile Ranking'!D134/3+'Percentile Ranking'!E134/3 -> 0.754 | D5: ='Percentile Ranking'!F134*0.25+'Percentile Ranking'!G134*0.25+'Percentile Ranking'!H134*0.25+'Percentile Ranking'!I134*0.25 -> 0.632 | E5: ='Percentile Ranking'!J134/3 + 'Percentile Ranking'!K134/3 + 'Percentile Ranking'!L134/3 -> 0.903 | F5: ='Percentile Ranking'!M134/3 + 'Percentile Ranking'!N134/3 + 'Percentile Ranking'!O134/3 -> 0.846 | G5: =C5 * 0.25 + D5 * 0.25 + E5 * 0.25 + F5 * 0.25 -> 0.78375
B6: INDRAPRASTHA GAS LTD | C6: ='Percentile Ranking'!C97/3+'Percentile Ranking'!D97/3+'Percentile Ranking'!E97/3 -> 0.638 | D6: ='Percentile Ranking'!F97*0.25+'Percentile Ranking'!G97*0.25+'Percentile Ranking'!H97*0.25+'Percentile Ranking'!I97*0.25 -> 0.78275 | E6: ='Percentile Ranking'!J97/3 + 'Percentile Ranking'!K97/3 + 'Percentile Ranking'!L97/3 -> 0.859 | F6: ='Percentile Ranking'!M97/3 + 'Percentile Ranking'!N97/3 + 'Percentile Ranking'!O97/3 -> 0.789 | G6: =C6 * 0.25 + D6 * 0.25 + E6 * 0.25 + F6 * 0.25 -> 0.7671875
B7: TATA ELXSI LTD | C7: ='Percentile Ranking'!C180/3+'Percentile Ranking'!D180/3+'Percentile Ranking'!E180/3 -> 0.73066667 | D7: ='Percentile Ranking'!F180*0.25+'Percentile Ranking'!G180*0.25+'Percentile Ranking'!H180*0.25+'Percentile Ranking'!I180*0.25 -> 0.8985 | E7: ='Percentile Ranking'!J180/3 + 'Percentile Ranking'!K180/3 + 'Percentile Ranking'!L180/3 -> 0.76066667 | F7: ='Percentile Ranking'!M180/3 + 'Percentile Ranking'!N180/3 + 'Percentile Ranking'!O180/3 -> 0.54933333 | G7: =C7 * 0.25 + D7 * 0.25 + E7 * 0.25 + F7 * 0.25 -> 0.73479167
B8: NMDC LTD | C8: ='Percentile Ranking'!C137/3+'Percentile Ranking'!D137/3+'Percentile Ranking'!E137/3 -> 0.608 | D8: ='Percentile Ranking'!F137*0.25+'Percentile Ranking'!G137*0.25+'Percentile Ranking'!H137*0.25+'Percentile Ranking'!I137*0.25 -> 0.7675 | E8: ='Percentile Ranking'!J137/3 + 'Percentile Ranking'!K137/3 + 'Percentile Ranking'!L137/3 -> 0.75833333 | F8: ='Percentile Ranking'!M137/3 + 'Percentile Ranking'!N137/3 + 'Percentile Ranking'!O137/3 -> 0.78233333 | G8: =C8 * 0.25 + D8 * 0.25 + E8 * 0.25 + F8 * 0.25 -> 0.72904167
B9: SUPREME INDUSTRIES LTD | C9: ='Percentile Ranking'!C174/3+'Percentile Ranking'!D174/3+'Percentile Ranking'!E174/3 -> 0.68366667 | D9: ='Percentile Ranking'!F174*0.25+'Percentile Ranking'!G174*0.25+'Percentile Ranking'!H174*0.25+'Percentile Ranking'!I174*0.25 -> 0.869 | E9: ='Percentile Ranking'!J174/3 + 'Percentile Ranking'!K174/3 + 'Percentile Ranking'!L174/3 -> 0.72533333 | F9: ='Percentile Ranking'!M174/3 + 'Percentile Ranking'!N174/3 + 'Percentile Ranking'!O174/3 -> 0.56433333 | G9: =C9 * 0.25 + D9 * 0.25 + E9 * 0.25 + F9 * 0.25 -> 0.71058333
B10: HDFC ASSET MANAGEMENT COMPANY LTD | C10: ='Percentile Ranking'!C76/3+'Percentile Ranking'!D76/3+'Percentile Ranking'!E76/3 -> 0.70366667 | D10: ='Percentile Ranking'!F76*0.25+'Percentile Ranking'!G76*0.25+'Percentile Ranking'!H76*0.25+'Percentile Ranking'!I76*0.25 -> 0.80175 | E10: ='Percentile Ranking'!J76/3 + 'Percentile Ranking'!K76/3 + 'Percentile Ranking'!L76/3 -> 0.933 | F10: ='Percentile Ranking'!M76/3 + 'Percentile Ranking'!N76/3 + 'Percentile Ranking'!O76/3 -> 0.39366667 | G10: =C10 * 0.25 + D10 * 0.25 + E10 * 0.25 + F10 * 0.25 -> 0.70802083
B11: INDUS TOWERS LTD | C11: ='Percentile Ranking'!C98/3+'Percentile Ranking'!D98/3+'Percentile Ranking'!E98/3 -> 0.88766667 | D11: ='Percentile Ranking'!F98*0.25+'Percentile Ranking'!G98*0.25+'Percentile Ranking'!H98*0.25+'Percentile Ranking'!I98*0.25 -> 0.642 | E11: ='Percentile Ranking'!J98/3 + 'Percentile Ranking'!K98/3 + 'Percentile Ranking'!L98/3 -> 0.48233333 | F11: ='Percentile Ranking'!M98/3 + 'Percentile Ranking'!N98/3 + 'Percentile Ranking'!O98/3 -> 0.80066667 | G11: =C11 * 0.25 + D11 * 0.25 + E11 * 0.25 + F11 * 0.25 -> 0.70316667
B12: INFOSYS LTD | C12: ='Percentile Ranking'!C101/3+'Percentile Ranking'!D101/3+'Percentile Ranking'!E101/3 -> 0.44733333 | D12: ='Percentile Ranking'!F101*0.25+'Percentile Ranking'!G101*0.25+'Percentile Ranking'!H101*0.25+'Percentile Ranking'!I101*0.25 -> 0.88225 | E12: ='Percentile Ranking'!J101/3 + 'Percentile Ranking'!K101/3 + 'Percentile Ranking'!L101/3 -> 0.799 | F12: ='Percentile Ranking'!M101/3 + 'Percentile Ranking'!N101/3 + 'Percentile Ranking'!O101/3 -> 0.65633333 | G12: =C12 * 0.25 + D12 * 0.25 + E12 * 0.25 + F12 * 0.25 -> 0.69622917
B13: INFO EDGE (INDIA) LTD | C13: ='Percentile Ranking'!C100/3+'Percentile Ranking'!D100/3+'Percentile Ranking'!E100/3 -> 0.82766667 | D13: ='Percentile Ranking'!F100*0.25+'Percentile Ranking'!G100*0.25+'Percentile Ranking'!H100*0.25+'Percentile Ranking'!I100*0.25 -> 0.466 | E13: ='Percentile Ranking'!J100/3 + 'Percentile Ranking'!K100/3 + 'Percentile Ranking'!L100/3 -> 0.83066667 | F13: ='Percentile Ranking'!M100/3 + 'Percentile Ranking'!N100/3 + 'Percentile Ranking'!O100/3 -> 0.59333333 | G13: =C13 * 0.25 + D13 * 0.25 + E13 * 0.25 + F13 * 0.25 -> 0.67941667
B14: PERSISTENT SYSTEMS LTD | C14: ='Percentile Ranking'!C149/3+'Percentile Ranking'!D149/3+'Percentile Ranking'!E149/3 -> 0.82433333 | D14: ='Percentile Ranking'!F149*0.25+'Percentile Ranking'!G149*0.25+'Percentile Ranking'!H149*0.25+'Percentile Ranking'!I149*0.25 -> 0.81275 | E14: ='Percentile Ranking'!J149/3 + 'Percentile Ranking'!K149/3 + 'Percentile Ranking'!L149/3 -> 0.881 | F14: ='Percentile Ranking'!M149/3 + 'Percentile Ranking'!N149/3 + 'Percentile Ranking'!O149/3 -> 0.17433333 | G14: =C14 * 0.25 + D14 * 0.25 + E14 * 0.25 + F14 * 0.25 -> 0.67310417
B15: BHARAT ELECTRONICS LTD | C15: ='Percentile Ranking'!C34/3+'Percentile Ranking'!D34/3+'Percentile Ranking'!E34/3 -> 0.725 | D15: ='Percentile Ranking'!F34*0.25+'Percentile Ranking'!G34*0.25+'Percentile Ranking'!H34*0.25+'Percentile Ranking'!I34*0.25 -> 0.682 | E15: ='Percentile Ranking'!J34/3 + 'Percentile Ranking'!K34/3 + 'Percentile Ranking'!L34/3 -> 0.913 | F15: ='Percentile Ranking'!M34/3 + 'Percentile Ranking'!N34/3 + 'Percentile Ranking'!O34/3 -> 0.36166667 | G15: =C15 * 0.25 + D15 * 0.25 + E15 * 0.25 + F15 * 0.25 -> 0.67041667
B16: ORACLE FINANCIAL SERVICES SOFTWARE LTD | C16: ='Percentile Ranking'!C144/3+'Percentile Ranking'!D144/3+'Percentile Ranking'!E144/3 -> 0.41033333 | D16: ='Percentile Ranking'!F144*0.25+'Percentile Ranking'!G144*0.25+'Percentile Ranking'!H144*0.25+'Percentile Ranking'!I144*0.25 -> 0.84425 | E16: ='Percentile Ranking'!J144/3 + 'Percentile Ranking'!K144/3 + 'Percentile Ranking'!L144/3 -> 0.923 | F16: ='Percentile Ranking'!M144/3 + 'Percentile Ranking'!N144/3 + 'Percentile Ranking'!O144/3 -> 0.50266667 | G16: =C16 * 0.25 + D16 * 0.25 + E16 * 0.25 + F16 * 0.25 -> 0.6700625
B17: HERO MOTOCORP LTD | C17: ='Percentile Ranking'!C79/3+'Percentile Ranking'!D79/3+'Percentile Ranking'!E79/3 -> 0.253 | D17: ='Percentile Ranking'!F79*0.25+'Percentile Ranking'!G79*0.25+'Percentile Ranking'!H79*0.25+'Percentile Ranking'!I79*0.25 -> 0.879 | E17: ='Percentile Ranking'!J79/3 + 'Percentile Ranking'!K79/3 + 'Percentile Ranking'!L79/3 -> 0.89433333 | F17: ='Percentile Ranking'!M79/3 + 'Percentile Ranking'!N79/3 + 'Percentile Ranking'!O79/3 -> 0.648 | G17: =C17 * 0.25 + D17 * 0.25 + E17 * 0.25 + F17 * 0.25 -> 0.66858333
B18: P I INDUSTRIES LTD | C18: ='Percentile Ranking'!C145/3+'Percentile Ranking'!D145/3+'Percentile Ranking'!E145/3 -> 0.79233333 | D18: ='Percentile Ranking'!F145*0.25+'Percentile Ranking'!G145*0.25+'Percentile Ranking'!H145*0.25+'Percentile Ranking'!I145*0.25 -> 0.69975 | E18: ='Percentile Ranking'!J145/3 + 'Percentile Ranking'!K145/3 + 'Percentile Ranking'!L145/3 -> 0.727 | F18: ='Percentile Ranking'!M145/3 + 'Percentile Ranking'!N145/3 + 'Percentile Ranking'!O145/3 -> 0.45233333 | G18: =C18 * 0.25 + D18 * 0.25 + E18 * 0.25 + F18 * 0.25 -> 0.66785417
B19: INDIAN RAILWAY CATERING & TOURISM CORPORATION LTD | C19: ='Percentile Ranking'!C94/3+'Percentile Ranking'!D94/3+'Percentile Ranking'!E94/3 -> 0.81933333 | D19: ='Percentile Ranking'!F94*0.25+'Percentile Ranking'!G94*0.25+'Percentile Ranking'!H94*0.25+'Percentile Ranking'!I94*0.25 -> 0.81425 | E19: ='Percentile Ranking'!J94/3 + 'Percentile Ranking'!K94/3 + 'Percentile Ranking'!L94/3 -> 0.78233333 | F19: ='Percentile Ranking'!M94/3 + 'Percentile Ranking'!N94/3 + 'Percentile Ranking'!O94/3 -> 0.253 | G19: =C19 * 0.25 + D19 * 0.25 + E19 * 0.25 + F19 * 0.25 -> 0.66722917
B20: ITC LTD | C20: ='Percentile Ranking'!C105/3+'Percentile Ranking'!D105/3+'Percentile Ranking'!E105/3 -> 0.43233333 | D20: ='Percentile Ranking'!F105*0.25+'Percentile Ranking'!G105*0.25+'Percentile Ranking'!H105*0.25+'Percentile Ranking'!I105*0.25 -> 0.76375 | E20: ='Percentile Ranking'!J105/3 + 'Percentile Ranking'!K105/3 + 'Percentile Ranking'!L105/3 -> 0.92633333 | F20: ='Percentile Ranking'!M105/3 + 'Percentile Ranking'!N105/3 + 'Percentile Ranking'!O105/3 -> 0.54266667 | G20: =C20 * 0.25 + D20 * 0.25 + E20 * 0.25 + F20 * 0.25 -> 0.66627083
B21: HCL TECHNOLOGIES LTD | C21: ='Percentile Ranking'!C75/3+'Percentile Ranking'!D75/3+'Percentile Ranking'!E75/3 -> 0.643 | D21: ='Percentile Ranking'!F75*0.25+'Percentile Ranking'!G75*0.25+'Percentile Ranking'!H75*0.25+'Percentile Ranking'!I75*0.25 -> 0.87925 | E21: ='Percentile Ranking'!J75/3 + 'Percentile Ranking'!K75/3 + 'Percentile Ranking'!L75/3 -> 0.854 | F21: ='Percentile Ranking'!M75/3 + 'Percentile Ranking'!N75/3 + 'Percentile Ranking'!O75/3 -> 0.27466667 | G21: =C21 * 0.25 + D21 * 0.25 + E21 * 0.25 + F21 * 0.25 -> 0.66272917
B22: EICHER MOTORS LTD | C22: ='Percentile Ranking'!C61/3+'Percentile Ranking'!D61/3+'Percentile Ranking'!E61/3 -> 0.58633333 | D22: ='Percentile Ranking'!F61*0.25+'Percentile Ranking'!G61*0.25+'Percentile Ranking'!H61*0.25+'Percentile Ranking'!I61*0.25 -> 0.809 | E22: ='Percentile Ranking'!J61/3 + 'Percentile Ranking'!K61/3 + 'Percentile Ranking'!L61/3 -> 0.89266667 | F22: ='Percentile Ranking'!M61/3 + 'Percentile Ranking'!N61/3 + 'Percentile Ranking'!O61/3 -> 0.355 | G22: =C22 * 0.25 + D22 * 0.25 + E22 * 0.25 + F22 * 0.25 -> 0.66075
B23: GAIL (INDIA) LTD | C23: ='Percentile Ranking'!C67/3+'Percentile Ranking'!D67/3+'Percentile Ranking'!E67/3 -> 0.64666667 | D23: ='Percentile Ranking'!F67*0.25+'Percentile Ranking'!G67*0.25+'Percentile Ranking'!H67*0.25+'Percentile Ranking'!I67*0.25 -> 0.6105 | E23: ='Percentile Ranking'!J67/3 + 'Percentile Ranking'!K67/3 + 'Percentile Ranking'!L67/3 -> 0.57633333 | F23: ='Percentile Ranking'!M67/3 + 'Percentile Ranking'!N67/3 + 'Percentile Ranking'!O67/3 -> 0.79733333 | G23: =C23 * 0.25 + D23 * 0.25 + E23 * 0.25 + F23 * 0.25 -> 0.65770833
B24: POLYCAB INDIA LTD | C24: ='Percentile Ranking'!C152/3+'Percentile Ranking'!D152/3+'Percentile Ranking'!E152/3 -> 0.86933333 | D24: ='Percentile Ranking'!F152*0.25+'Percentile Ranking'!G152*0.25+'Percentile Ranking'!H152*0.25+'Percentile Ranking'!I152*0.25 -> 0.8055 | E24: ='Percentile Ranking'!J152/3 + 'Percentile Ranking'!K152/3 + 'Percentile Ranking'!L152/3 -> 0.59966667 | F24: ='Percentile Ranking'!M152/3 + 'Percentile Ranking'!N152/3 + 'Percentile Ranking'!O152/3 -> 0.35366667 | G24: =C24 * 0.25 + D24 * 0.25 + E24 * 0.25 + F24 * 0.25 -> 0.65704167
B25: BSE LTD | C25: ='Percentile Ranking'!C44/3+'Percentile Ranking'!D44/3+'Percentile Ranking'!E44/3 -> 0.898 | D25: ='Percentile Ranking'!F44*0.25+'Percentile Ranking'!G44*0.25+'Percentile Ranking'!H44*0.25+'Percentile Ranking'!I44*0.25 -> 0.52025 | E25: ='Percentile Ranking'!J44/3 + 'Percentile Ranking'!K44/3 + 'Percentile Ranking'!L44/3 -> 0.95466667 | F25: ='Percentile Ranking'!M44/3 + 'Percentile Ranking'!N44/3 + 'Percentile Ranking'!O44/3 -> 0.248 | G25: =C25 * 0.25 + D25 * 0.25 + E25 * 0.25 + F25 * 0.25 -> 0.65522917
B26: MPHASIS LTD | C26: ='Percentile Ranking'!C131/3+'Percentile Ranking'!D131/3+'Percentile Ranking'!E131/3 -> 0.66833333 | D26: ='Percentile Ranking'!F131*0.25+'Percentile Ranking'!G131*0.25+'Percentile Ranking'!H131*0.25+'Percentile Ranking'!I131*0.25 -> 0.83925 | E26: ='Percentile Ranking'!J131/3 + 'Percentile Ranking'!K131/3 + 'Percentile Ranking'!L131/3 -> 0.75733333 | F26: ='Percentile Ranking'!M131/3 + 'Percentile Ranking'!N131/3 + 'Percentile Ranking'!O131/3 -> 0.352 | G26: =C26 * 0.25 + D26 * 0.25 + E26 * 0.25 + F26 * 0.25 -> 0.65422917
B27: TATA STEEL LTD | C27: ='Percentile Ranking'!C183/3+'Percentile Ranking'!D183/3+'Percentile Ranking'!E183/3 -> 0.79266667 | D27: ='Percentile Ranking'!F183*0.25+'Percentile Ranking'!G183*0.25+'Percentile Ranking'!H183*0.25+'Percentile Ranking'!I183*0.25 -> 0.52025 | E27: ='Percentile Ranking'!J183/3 + 'Percentile Ranking'!K183/3 + 'Percentile Ranking'!L183/3 -> 0.39866667 | F27: ='Percentile Ranking'!M183/3 + 'Percentile Ranking'!N183/3 + 'Percentile Ranking'!O183/3 -> 0.871 | G27: =C27 * 0.25 + D27 * 0.25 + E27 * 0.25 + F27 * 0.25 -> 0.64564583
B28: ASIAN PAINTS LTD | C28: ='Percentile Ranking'!C20/3+'Percentile Ranking'!D20/3+'Percentile Ranking'!E20/3 -> 0.47066667 | D28: ='Percentile Ranking'!F20*0.25+'Percentile Ranking'!G20*0.25+'Percentile Ranking'!H20*0.25+'Percentile Ranking'!I20*0.25 -> 0.8615 | E28: ='Percentile Ranking'!J20/3 + 'Percentile Ranking'!K20/3 + 'Percentile Ranking'!L20/3 -> 0.76066667 | F28: ='Percentile Ranking'!M20/3 + 'Percentile Ranking'!N20/3 + 'Percentile Ranking'!O20/3 -> 0.46066667 | G28: =C28 * 0.25 + D28 * 0.25 + E28 * 0.25 + F28 * 0.25 -> 0.638375
B29: BAJAJ AUTO LTD | C29: ='Percentile Ranking'!C26/3+'Percentile Ranking'!D26/3+'Percentile Ranking'!E26/3 -> 0.40866667 | D29: ='Percentile Ranking'!F26*0.25+'Percentile Ranking'!G26*0.25+'Percentile Ranking'!H26*0.25+'Percentile Ranking'!I26*0.25 -> 0.84675 | E29: ='Percentile Ranking'!J26/3 + 'Percentile Ranking'!K26/3 + 'Percentile Ranking'!L26/3 -> 0.901 | F29: ='Percentile Ranking'!M26/3 + 'Percentile Ranking'!N26/3 + 'Percentile Ranking'!O26/3 -> 0.39533333 | G29: =C29 * 0.25 + D29 * 0.25 + E29 * 0.25 + F29 * 0.25 -> 0.6379375
B30: NESTLE INDIA LTD | C30: ='Percentile Ranking'!C135/3+'Percentile Ranking'!D135/3+'Percentile Ranking'!E135/3 -> 0.50066667 | D30: ='Percentile Ranking'!F135*0.25+'Percentile Ranking'!G135*0.25+'Percentile Ranking'!H135*0.25+'Percentile Ranking'!I135*0.25 -> 0.97375 | E30: ='Percentile Ranking'!J135/3 + 'Percentile Ranking'!K135/3 + 'Percentile Ranking'!L135/3 -> 0.68166667 | F30: ='Percentile Ranking'!M135/3 + 'Percentile Ranking'!N135/3 + 'Percentile Ranking'!O135/3 -> 0.395 | G30: =C30 * 0.25 + D30 * 0.25 + E30 * 0.25 + F30 * 0.25 -> 0.63777083
B31: TATA CONSULTANCY SERVICES LTD | C31: ='Percentile Ranking'!C178/3+'Percentile Ranking'!D178/3+'Percentile Ranking'!E178/3 -> 0.45066667 | D31: ='Percentile Ranking'!F178*0.25+'Percentile Ranking'!G178*0.25+'Percentile Ranking'!H178*0.25+'Percentile Ranking'!I178*0.25 -> 0.96375 | E31: ='Percentile Ranking'!J178/3 + 'Percentile Ranking'!K178/3 + 'Percentile Ranking'!L178/3 -> 0.82766667 | F31: ='Percentile Ranking'!M178/3 + 'Percentile Ranking'!N178/3 + 'Percentile Ranking'!O178/3 -> 0.29633333 | G31: =C31 * 0.25 + D31 * 0.25 + E31 * 0.25 + F31 * 0.25 -> 0.63460417
B32: MOTILAL OSWAL FINANCIAL SERVICES LTD | C32: ='Percentile Ranking'!C130/3+'Percentile Ranking'!D130/3+'Percentile Ranking'!E130/3 -> 0.99 | D32: ='Percentile Ranking'!F130*0.25+'Percentile Ranking'!G130*0.25+'Percentile Ranking'!H130*0.25+'Percentile Ranking'!I130*0.25 -> 0.45575 | E32: ='Percentile Ranking'!J130/3 + 'Percentile Ranking'!K130/3 + 'Percentile Ranking'!L130/3 -> 0.337 | F32: ='Percentile Ranking'!M130/3 + 'Percentile Ranking'!N130/3 + 'Percentile Ranking'!O130/3 -> 0.73866667 | G32: =C32 * 0.25 + D32 * 0.25 + E32 * 0.25 + F32 * 0.25 -> 0.63035417
B33: CIPLA LTD | C33: ='Percentile Ranking'!C48/3+'Percentile Ranking'!D48/3+'Percentile Ranking'!E48/3 -> 0.474 | D33: ='Percentile Ranking'!F48*0.25+'Percentile Ranking'!G48*0.25+'Percentile Ranking'!H48*0.25+'Percentile Ranking'!I48*0.25 -> 0.57425 | E33: ='Percentile Ranking'!J48/3 + 'Percentile Ranking'!K48/3 + 'Percentile Ranking'!L48/3 -> 0.86933333 | F33: ='Percentile Ranking'!M48/3 + 'Percentile Ranking'!N48/3 + 'Percentile Ranking'!O48/3 -> 0.601 | G33: =C33 * 0.25 + D33 * 0.25 + E33 * 0.25 + F33 * 0.25 -> 0.62964583
B34: ICICI LOMBARD GENERAL INSURANCE COMPANY LTD | C34: ='Percentile Ranking'!C89/3+'Percentile Ranking'!D89/3+'Percentile Ranking'!E89/3 -> 0.769 | D34: ='Percentile Ranking'!F89*0.25+'Percentile Ranking'!G89*0.25+'Percentile Ranking'!H89*0.25+'Percentile Ranking'!I89*0.25 -> 0.5255 | E34: ='Percentile Ranking'!J89/3 + 'Percentile Ranking'!K89/3 + 'Percentile Ranking'!L89/3 -> 0.75233333 | F34: ='Percentile Ranking'!M89/3 + 'Percentile Ranking'!N89/3 + 'Percentile Ranking'!O89/3 -> 0.46566667 | G34: =C34 * 0.25 + D34 * 0.25 + E34 * 0.25 + F34 * 0.25 -> 0.628125
B35: DR REDDYS LABORATORIES LTD | C35: ='Percentile Ranking'!C60/3+'Percentile Ranking'!D60/3+'Percentile Ranking'!E60/3 -> 0.59766667 | D35: ='Percentile Ranking'!F60*0.25+'Percentile Ranking'!G60*0.25+'Percentile Ranking'!H60*0.25+'Percentile Ranking'!I60*0.25 -> 0.56675 | E35: ='Percentile Ranking'!J60/3 + 'Percentile Ranking'!K60/3 + 'Percentile Ranking'!L60/3 -> 0.64666667 | F35: ='Percentile Ranking'!M60/3 + 'Percentile Ranking'!N60/3 + 'Percentile Ranking'!O60/3 -> 0.67166667 | G35: =C35 * 0.25 + D35 * 0.25 + E35 * 0.25 + F35 * 0.25 -> 0.6206875
B36: MAZAGON DOCK SHIPBUILDERS LTD | C36: ='Percentile Ranking'!C129/3+'Percentile Ranking'!D129/3+'Percentile Ranking'!E129/3 -> 0.75033333 | D36: ='Percentile Ranking'!F129*0.25+'Percentile Ranking'!G129*0.25+'Percentile Ranking'!H129*0.25+'Percentile Ranking'!I129*0.25 -> 0.60175 | E36: ='Percentile Ranking'!J129/3 + 'Percentile Ranking'!K129/3 + 'Percentile Ranking'!L129/3 -> 0.87266667 | F36: ='Percentile Ranking'!M129/3 + 'Percentile Ranking'!N129/3 + 'Percentile Ranking'!O129/3 -> 0.255 | G36: =C36 * 0.25 + D36 * 0.25 + E36 * 0.25 + F36 * 0.25 -> 0.6199375
B37: ASTRAL LTD | C37: ='Percentile Ranking'!C21/3+'Percentile Ranking'!D21/3+'Percentile Ranking'!E21/3 -> 0.839 | D37: ='Percentile Ranking'!F21*0.25+'Percentile Ranking'!G21*0.25+'Percentile Ranking'!H21*0.25+'Percentile Ranking'!I21*0.25 -> 0.73375 | E37: ='Percentile Ranking'!J21/3 + 'Percentile Ranking'!K21/3 + 'Percentile Ranking'!L21/3 -> 0.663 | F37: ='Percentile Ranking'!M21/3 + 'Percentile Ranking'!N21/3 + 'Percentile Ranking'!O21/3 -> 0.23766667 | G37: =C37 * 0.25 + D37 * 0.25 + E37 * 0.25 + F37 * 0.25 -> 0.61835417
B38: KEI INDUSTRIES LTD | C38: ='Percentile Ranking'!C112/3+'Percentile Ranking'!D112/3+'Percentile Ranking'!E112/3 -> 0.831 | D38: ='Percentile Ranking'!F112*0.25+'Percentile Ranking'!G112*0.25+'Percentile Ranking'!H112*0.25+'Percentile Ranking'!I112*0.25 -> 0.7665 | E38: ='Percentile Ranking'!J112/3 + 'Percentile Ranking'!K112/3 + 'Percentile Ranking'!L112/3 -> 0.442 | F38: ='Percentile Ranking'!M112/3 + 'Percentile Ranking'!N112/3 + 'Percentile Ranking'!O112/3 -> 0.42566667 | G38: =C38 * 0.25 + D38 * 0.25 + E38 * 0.25 + F38 * 0.25 -> 0.61629167
B39: TITAN COMPANY LTD | C39: ='Percentile Ranking'!C186/3+'Percentile Ranking'!D186/3+'Percentile Ranking'!E186/3 -> 0.814 | D39: ='Percentile Ranking'!F186*0.25+'Percentile Ranking'!G186*0.25+'Percentile Ranking'!H186*0.25+'Percentile Ranking'!I186*0.25 -> 0.784 | E39: ='Percentile Ranking'!J186/3 + 'Percentile Ranking'!K186/3 + 'Percentile Ranking'!L186/3 -> 0.43233333 | F39: ='Percentile Ranking'!M186/3 + 'Percentile Ranking'!N186/3 + 'Percentile Ranking'!O186/3 -> 0.43233333 | G39: =C39 * 0.25 + D39 * 0.25 + E39 * 0.25 + F39 * 0.25 -> 0.61566667
B40: AVENUE SUPERMARTS LTD | C40: ='Percentile Ranking'!C24/3+'Percentile Ranking'!D24/3+'Percentile Ranking'!E24/3 -> 0.908 | D40: ='Percentile Ranking'!F24*0.25+'Percentile Ranking'!G24*0.25+'Percentile Ranking'!H24*0.25+'Percentile Ranking'!I24*0.25 -> 0.73125 | E40: ='Percentile Ranking'!J24/3 + 'Percentile Ranking'!K24/3 + 'Percentile Ranking'!L24/3 -> 0.66633333 | F40: ='Percentile Ranking'!M24/3 + 'Percentile Ranking'!N24/3 + 'Percentile Ranking'!O24/3 -> 0.15566667 | G40: =C40 * 0.25 + D40 * 0.25 + E40 * 0.25 + F40 * 0.25 -> 0.6153125
B41: ACC LTD | C41: ='Percentile Ranking'!C7/3+'Percentile Ranking'!D7/3+'Percentile Ranking'!E7/3 -> 0.454 | D41: ='Percentile Ranking'!F7*0.25+'Percentile Ranking'!G7*0.25+'Percentile Ranking'!H7*0.25+'Percentile Ranking'!I7*0.25 -> 0.534 | E41: ='Percentile Ranking'!J7/3 + 'Percentile Ranking'!K7/3 + 'Percentile Ranking'!L7/3 -> 0.757 | F41: ='Percentile Ranking'!M7/3 + 'Percentile Ranking'!N7/3 + 'Percentile Ranking'!O7/3 -> 0.70833333 | G41: =C41 * 0.25 + D41 * 0.25 + E41 * 0.25 + F41 * 0.25 -> 0.61333333
B42: MARUTI SUZUKI INDIA LTD | C42: ='Percentile Ranking'!C126/3+'Percentile Ranking'!D126/3+'Percentile Ranking'!E126/3 -> 0.469 | D42: ='Percentile Ranking'!F126*0.25+'Percentile Ranking'!G126*0.25+'Percentile Ranking'!H126*0.25+'Percentile Ranking'!I126*0.25 -> 0.67975 | E42: ='Percentile Ranking'!J126/3 + 'Percentile Ranking'!K126/3 + 'Percentile Ranking'!L126/3 -> 0.831 | F42: ='Percentile Ranking'!M126/3 + 'Percentile Ranking'!N126/3 + 'Percentile Ranking'!O126/3 -> 0.47233333 | G42: =C42 * 0.25 + D42 * 0.25 + E42 * 0.25 + F42 * 0.25 -> 0.61302083
B43: BHARAT PETROLEUM CORPORATION LTD | C43: ='Percentile Ranking'!C37/3+'Percentile Ranking'!D37/3+'Percentile Ranking'!E37/3 -> 0.42866667 | D43: ='Percentile Ranking'!F37*0.25+'Percentile Ranking'!G37*0.25+'Percentile Ranking'!H37*0.25+'Percentile Ranking'!I37*0.25 -> 0.75375 | E43: ='Percentile Ranking'!J37/3 + 'Percentile Ranking'!K37/3 + 'Percentile Ranking'!L37/3 -> 0.38033333 | F43: ='Percentile Ranking'!M37/3 + 'Percentile Ranking'!N37/3 + 'Percentile Ranking'!O37/3 -> 0.86633333 | G43: =C43 * 0.25 + D43 * 0.25 + E43 * 0.25 + F43 * 0.25 -> 0.60727083
B44: GODFREY PHILLIPS INDIA LTD | C44: ='Percentile Ranking'!C70/3+'Percentile Ranking'!D70/3+'Percentile Ranking'!E70/3 -> 0.65633333 | D44: ='Percentile Ranking'!F70*0.25+'Percentile Ranking'!G70*0.25+'Percentile Ranking'!H70*0.25+'Percentile Ranking'!I70*0.25 -> 0.6935 | E44: ='Percentile Ranking'!J70/3 + 'Percentile Ranking'!K70/3 + 'Percentile Ranking'!L70/3 -> 0.695 | F44: ='Percentile Ranking'!M70/3 + 'Percentile Ranking'!N70/3 + 'Percentile Ranking'!O70/3 -> 0.37366667 | G44: =C44 * 0.25 + D44 * 0.25 + E44 * 0.25 + F44 * 0.25 -> 0.604625
B45: HINDUSTAN ZINC LTD | C45: ='Percentile Ranking'!C84/3+'Percentile Ranking'!D84/3+'Percentile Ranking'!E84/3 -> 0.439 | D45: ='Percentile Ranking'!F84*0.25+'Percentile Ranking'!G84*0.25+'Percentile Ranking'!H84*0.25+'Percentile Ranking'!I84*0.25 -> 0.88225 | E45: ='Percentile Ranking'!J84/3 + 'Percentile Ranking'!K84/3 + 'Percentile Ranking'!L84/3 -> 0.573 | F45: ='Percentile Ranking'!M84/3 + 'Percentile Ranking'!N84/3 + 'Percentile Ranking'!O84/3 -> 0.51266667 | G45: =C45 * 0.25 + D45 * 0.25 + E45 * 0.25 + F45 * 0.25 -> 0.60172917
B46: ADANI TOTAL GAS LTD | C46: ='Percentile Ranking'!C13/3+'Percentile Ranking'!D13/3+'Percentile Ranking'!E13/3 -> 0.85233333 | D46: ='Percentile Ranking'!F13*0.25+'Percentile Ranking'!G13*0.25+'Percentile Ranking'!H13*0.25+'Percentile Ranking'!I13*0.25 -> 0.68875 | E46: ='Percentile Ranking'!J13/3 + 'Percentile Ranking'!K13/3 + 'Percentile Ranking'!L13/3 -> 0.42366667 | F46: ='Percentile Ranking'!M13/3 + 'Percentile Ranking'!N13/3 + 'Percentile Ranking'!O13/3 -> 0.43566667 | G46: =C46 * 0.25 + D46 * 0.25 + E46 * 0.25 + F46 * 0.25 -> 0.60010417
B47: COAL INDIA LTD | C47: ='Percentile Ranking'!C49/3+'Percentile Ranking'!D49/3+'Percentile Ranking'!E49/3 -> 0.41533333 | D47: ='Percentile Ranking'!F49*0.25+'Percentile Ranking'!G49*0.25+'Percentile Ranking'!H49*0.25+'Percentile Ranking'!I49*0.25 -> 0.848 | E47: ='Percentile Ranking'!J49/3 + 'Percentile Ranking'!K49/3 + 'Percentile Ranking'!L49/3 -> 0.97 | F47: ='Percentile Ranking'!M49/3 + 'Percentile Ranking'!N49/3 + 'Percentile Ranking'!O49/3 -> 0.16266667 | G47: =C47 * 0.25 + D47 * 0.25 + E47 * 0.25 + F47 * 0.25 -> 0.599
B48: COFORGE LTD | C48: ='Percentile Ranking'!C51/3+'Percentile Ranking'!D51/3+'Percentile Ranking'!E51/3 -> 0.521 | D48: ='Percentile Ranking'!F51*0.25+'Percentile Ranking'!G51*0.25+'Percentile Ranking'!H51*0.25+'Percentile Ranking'!I51*0.25 -> 0.80525 | E48: ='Percentile Ranking'!J51/3 + 'Percentile Ranking'!K51/3 + 'Percentile Ranking'!L51/3 -> 0.66666667 | F48: ='Percentile Ranking'!M51/3 + 'Percentile Ranking'!N51/3 + 'Percentile Ranking'!O51/3 -> 0.40033333 | G48: =C48 * 0.25 + D48 * 0.25 + E48 * 0.25 + F48 * 0.25 -> 0.5983125
B49: ADANI POWER LTD | C49: ='Percentile Ranking'!C12/3+'Percentile Ranking'!D12/3+'Percentile Ranking'!E12/3 -> 0.87933333 | D49: ='Percentile Ranking'!F12*0.25+'Percentile Ranking'!G12*0.25+'Percentile Ranking'!H12*0.25+'Percentile Ranking'!I12*0.25 -> 0.28525 | E49: ='Percentile Ranking'!J12/3 + 'Percentile Ranking'!K12/3 + 'Percentile Ranking'!L12/3 -> 0.46733333 | F49: ='Percentile Ranking'!M12/3 + 'Percentile Ranking'!N12/3 + 'Percentile Ranking'!O12/3 -> 0.75533333 | G49: =C49 * 0.25 + D49 * 0.25 + E49 * 0.25 + F49 * 0.25 -> 0.5968125
B50: EXIDE INDUSTRIES LTD | C50: ='Percentile Ranking'!C63/3+'Percentile Ranking'!D63/3+'Percentile Ranking'!E63/3 -> 0.39733333 | D50: ='Percentile Ranking'!F63*0.25+'Percentile Ranking'!G63*0.25+'Percentile Ranking'!H63*0.25+'Percentile Ranking'!I63*0.25 -> 0.662 | E50: ='Percentile Ranking'!J63/3 + 'Percentile Ranking'!K63/3 + 'Percentile Ranking'!L63/3 -> 0.78066667 | F50: ='Percentile Ranking'!M63/3 + 'Percentile Ranking'!N63/3 + 'Percentile Ranking'!O63/3 -> 0.54266667 | G50: =C50 * 0.25 + D50 * 0.25 + E50 * 0.25 + F50 * 0.25 -> 0.59566667
B51: DIXON TECHNOLOGIES (INDIA) LTD | C51: ='Percentile Ranking'!C58/3+'Percentile Ranking'!D58/3+'Percentile Ranking'!E58/3 -> 0.91633333 | D51: ='Percentile Ranking'!F58*0.25+'Percentile Ranking'!G58*0.25+'Percentile Ranking'!H58*0.25+'Percentile Ranking'!I58*0.25 -> 0.799 | E51: ='Percentile Ranking'!J58/3 + 'Percentile Ranking'!K58/3 + 'Percentile Ranking'!L58/3 -> 0.48066667 | F51: ='Percentile Ranking'!M58/3 + 'Percentile Ranking'!N58/3 + 'Percentile Ranking'!O58/3 -> 0.181 | G51: =C51 * 0.25 + D51 * 0.25 + E51 * 0.25 + F51 * 0.25 -> 0.59425
B52: APL APOLLO TUBES LTD | C52: ='Percentile Ranking'!C17/3+'Percentile Ranking'!D17/3+'Percentile Ranking'!E17/3 -> 0.861 | D52: ='Percentile Ranking'!F17*0.25+'Percentile Ranking'!G17*0.25+'Percentile Ranking'!H17*0.25+'Percentile Ranking'!I17*0.25 -> 0.67225 | E52: ='Percentile Ranking'!J17/3 + 'Percentile Ranking'!K17/3 + 'Percentile Ranking'!L17/3 -> 0.43033333 | F52: ='Percentile Ranking'!M17/3 + 'Percentile Ranking'!N17/3 + 'Percentile Ranking'!O17/3 -> 0.40233333 | G52: =C52 * 0.25 + D52 * 0.25 + E52 * 0.25 + F52 * 0.25 -> 0.59147917
B53: OIL & NATURAL GAS CORPN LTD | C53: ='Percentile Ranking'!C141/3+'Percentile Ranking'!D141/3+'Percentile Ranking'!E141/3 -> 0.35833333 | D53: ='Percentile Ranking'!F141*0.25+'Percentile Ranking'!G141*0.25+'Percentile Ranking'!H141*0.25+'Percentile Ranking'!I141*0.25 -> 0.53525 | E53: ='Percentile Ranking'!J141/3 + 'Percentile Ranking'!K141/3 + 'Percentile Ranking'!L141/3 -> 0.57633333 | F53: ='Percentile Ranking'!M141/3 + 'Percentile Ranking'!N141/3 + 'Percentile Ranking'!O141/3 -> 0.89633333 | G53: =C53 * 0.25 + D53 * 0.25 + E53 * 0.25 + F53 * 0.25 -> 0.5915625
B54: COROMANDEL INTERNATIONAL LTD | C54: ='Percentile Ranking'!C54/3+'Percentile Ranking'!D54/3+'Percentile Ranking'!E54/3 -> 0.59633333 | D54: ='Percentile Ranking'!F54*0.25+'Percentile Ranking'!G54*0.25+'Percentile Ranking'!H54*0.25+'Percentile Ranking'!I54*0.25 -> 0.81025 | E54: ='Percentile Ranking'!J54/3 + 'Percentile Ranking'!K54/3 + 'Percentile Ranking'!L54/3 -> 0.47933333 | F54: ='Percentile Ranking'!M54/3 + 'Percentile Ranking'!N54/3 + 'Percentile Ranking'!O54/3 -> 0.47566667 | G54: =C54 * 0.25 + D54 * 0.25 + E54 * 0.25 + F54 * 0.25 -> 0.59039583
B55: HINDUSTAN UNILEVER LTD | C55: ='Percentile Ranking'!C83/3+'Percentile Ranking'!D83/3+'Percentile Ranking'!E83/3 -> 0.43366667 | D55: ='Percentile Ranking'!F83*0.25+'Percentile Ranking'!G83*0.25+'Percentile Ranking'!H83*0.25+'Percentile Ranking'!I83*0.25 -> 0.8695 | E55: ='Percentile Ranking'!J83/3 + 'Percentile Ranking'!K83/3 + 'Percentile Ranking'!L83/3 -> 0.824 | F55: ='Percentile Ranking'!M83/3 + 'Percentile Ranking'!N83/3 + 'Percentile Ranking'!O83/3 -> 0.23433333 | G55: =C55 * 0.25 + D55 * 0.25 + E55 * 0.25 + F55 * 0.25 -> 0.590375
B56: BOSCH LTD | C56: ='Percentile Ranking'!C42/3+'Percentile Ranking'!D42/3+'Percentile Ranking'!E42/3 -> 0.28166667 | D56: ='Percentile Ranking'!F42*0.25+'Percentile Ranking'!G42*0.25+'Percentile Ranking'!H42*0.25+'Percentile Ranking'!I42*0.25 -> 0.6305 | E56: ='Percentile Ranking'!J42/3 + 'Percentile Ranking'!K42/3 + 'Percentile Ranking'!L42/3 -> 0.87266667 | F56: ='Percentile Ranking'!M42/3 + 'Percentile Ranking'!N42/3 + 'Percentile Ranking'!O42/3 -> 0.57266667 | G56: =C56 * 0.25 + D56 * 0.25 + E56 * 0.25 + F56 * 0.25 -> 0.589375
B57: TVS MOTOR COMPANY LTD | C57: ='Percentile Ranking'!C191/3+'Percentile Ranking'!D191/3+'Percentile Ranking'!E191/3 -> 0.76366667 | D57: ='Percentile Ranking'!F191*0.25+'Percentile Ranking'!G191*0.25+'Percentile Ranking'!H191*0.25+'Percentile Ranking'!I191*0.25 -> 0.73975 | E57: ='Percentile Ranking'!J191/3 + 'Percentile Ranking'!K191/3 + 'Percentile Ranking'!L191/3 -> 0.479 | F57: ='Percentile Ranking'!M191/3 + 'Percentile Ranking'!N191/3 + 'Percentile Ranking'!O191/3 -> 0.37033333 | G57: =C57 * 0.25 + D57 * 0.25 + E57 * 0.25 + F57 * 0.25 -> 0.5881875
B58: COLGATE-PALMOLIVE (INDIA) LTD | C58: ='Percentile Ranking'!C52/3+'Percentile Ranking'!D52/3+'Percentile Ranking'!E52/3 -> 0.36666667 | D58: ='Percentile Ranking'!F52*0.25+'Percentile Ranking'!G52*0.25+'Percentile Ranking'!H52*0.25+'Percentile Ranking'!I52*0.25 -> 0.9775 | E58: ='Percentile Ranking'!J52/3 + 'Percentile Ranking'!K52/3 + 'Percentile Ranking'!L52/3 -> 0.83266667 | F58: ='Percentile Ranking'!M52/3 + 'Percentile Ranking'!N52/3 + 'Percentile Ranking'!O52/3 -> 0.176 | G58: =C58 * 0.25 + D58 * 0.25 + E58 * 0.25 + F58 * 0.25 -> 0.58820833
B59: GODREJ PROPERTIES LTD | C59: ='Percentile Ranking'!C72/3+'Percentile Ranking'!D72/3+'Percentile Ranking'!E72/3 -> 0.95133333 | D59: ='Percentile Ranking'!F72*0.25+'Percentile Ranking'!G72*0.25+'Percentile Ranking'!H72*0.25+'Percentile Ranking'!I72*0.25 -> 0.19725 | E59: ='Percentile Ranking'!J72/3 + 'Percentile Ranking'!K72/3 + 'Percentile Ranking'!L72/3 -> 0.49233333 | F59: ='Percentile Ranking'!M72/3 + 'Percentile Ranking'!N72/3 + 'Percentile Ranking'!O72/3 -> 0.705 | G59: =C59 * 0.25 + D59 * 0.25 + E59 * 0.25 + F59 * 0.25 -> 0.58647917
B60: PAGE INDUSTRIES LTD | C60: ='Percentile Ranking'!C146/3+'Percentile Ranking'!D146/3+'Percentile Ranking'!E146/3 -> 0.56966667 | D60: ='Percentile Ranking'!F146*0.25+'Percentile Ranking'!G146*0.25+'Percentile Ranking'!H146*0.25+'Percentile Ranking'!I146*0.25 -> 0.96 | E60: ='Percentile Ranking'!J146/3 + 'Percentile Ranking'!K146/3 + 'Percentile Ranking'!L146/3 -> 0.613 | F60: ='Percentile Ranking'!M146/3 + 'Percentile Ranking'!N146/3 + 'Percentile Ranking'!O146/3 -> 0.19933333 | G60: =C60 * 0.25 + D60 * 0.25 + E60 * 0.25 + F60 * 0.25 -> 0.5855
B61: SOLAR INDUSTRIES INDIA LTD | C61: ='Percentile Ranking'!C168/3+'Percentile Ranking'!D168/3+'Percentile Ranking'!E168/3 -> 0.854 | D61: ='Percentile Ranking'!F168*0.25+'Percentile Ranking'!G168*0.25+'Percentile Ranking'!H168*0.25+'Percentile Ranking'!I168*0.25 -> 0.814 | E61: ='Percentile Ranking'!J168/3 + 'Percentile Ranking'!K168/3 + 'Percentile Ranking'!L168/3 -> 0.57966667 | F61: ='Percentile Ranking'!M168/3 + 'Percentile Ranking'!N168/3 + 'Percentile Ranking'!O168/3 -> 0.092333333 | G61: =C61 * 0.25 + D61 * 0.25 + E61 * 0.25 + F61 * 0.25 -> 0.585
B62: DIVIS LABORATORIES LTD | C62: ='Percentile Ranking'!C57/3+'Percentile Ranking'!D57/3+'Percentile Ranking'!E57/3 -> 0.439 | D62: ='Percentile Ranking'!F57*0.25+'Percentile Ranking'!G57*0.25+'Percentile Ranking'!H57*0.25+'Percentile Ranking'!I57*0.25 -> 0.691 | E62: ='Percentile Ranking'!J57/3 + 'Percentile Ranking'!K57/3 + 'Percentile Ranking'!L57/3 -> 0.92133333 | F62: ='Percentile Ranking'!M57/3 + 'Percentile Ranking'!N57/3 + 'Percentile Ranking'!O57/3 -> 0.28633333 | G62: =C62 * 0.25 + D62 * 0.25 + E62 * 0.25 + F62 * 0.25 -> 0.58441667
B63: MAHINDRA & MAHINDRA LTD | C63: ='Percentile Ranking'!C123/3+'Percentile Ranking'!D123/3+'Percentile Ranking'!E123/3 -> 0.67 | D63: ='Percentile Ranking'!F123*0.25+'Percentile Ranking'!G123*0.25+'Percentile Ranking'!H123*0.25+'Percentile Ranking'!I123*0.25 -> 0.525 | E63: ='Percentile Ranking'!J123/3 + 'Percentile Ranking'!K123/3 + 'Percentile Ranking'!L123/3 -> 0.62966667 | F63: ='Percentile Ranking'!M123/3 + 'Percentile Ranking'!N123/3 + 'Percentile Ranking'!O123/3 -> 0.50433333 | G63: =C63 * 0.25 + D63 * 0.25 + E63 * 0.25 + F63 * 0.25 -> 0.58225
B64: PIDILITE INDUSTRIES LTD | C64: ='Percentile Ranking'!C151/3+'Percentile Ranking'!D151/3+'Percentile Ranking'!E151/3 -> 0.51766667 | D64: ='Percentile Ranking'!F151*0.25+'Percentile Ranking'!G151*0.25+'Percentile Ranking'!H151*0.25+'Percentile Ranking'!I151*0.25 -> 0.824 | E64: ='Percentile Ranking'!J151/3 + 'Percentile Ranking'!K151/3 + 'Percentile Ranking'!L151/3 -> 0.81233333 | F64: ='Percentile Ranking'!M151/3 + 'Percentile Ranking'!N151/3 + 'Percentile Ranking'!O151/3 -> 0.171 | G64: =C64 * 0.25 + D64 * 0.25 + E64 * 0.25 + F64 * 0.25 -> 0.58125
B65: ALKEM LABORATORIES LTD | C65: ='Percentile Ranking'!C15/3+'Percentile Ranking'!D15/3+'Percentile Ranking'!E15/3 -> 0.53266667 | D65: ='Percentile Ranking'!F15*0.25+'Percentile Ranking'!G15*0.25+'Percentile Ranking'!H15*0.25+'Percentile Ranking'!I15*0.25 -> 0.67325 | E65: ='Percentile Ranking'!J15/3 + 'Percentile Ranking'!K15/3 + 'Percentile Ranking'!L15/3 -> 0.598 | F65: ='Percentile Ranking'!M15/3 + 'Percentile Ranking'!N15/3 + 'Percentile Ranking'!O15/3 -> 0.51566667 | G65: =C65 * 0.25 + D65 * 0.25 + E65 * 0.25 + F65 * 0.25 -> 0.57989583
B66: HAVELLS INDIA LTD | C66: ='Percentile Ranking'!C74/3+'Percentile Ranking'!D74/3+'Percentile Ranking'!E74/3 -> 0.58466667 | D66: ='Percentile Ranking'!F74*0.25+'Percentile Ranking'!G74*0.25+'Percentile Ranking'!H74*0.25+'Percentile Ranking'!I74*0.25 -> 0.79675 | E66: ='Percentile Ranking'!J74/3 + 'Percentile Ranking'!K74/3 + 'Percentile Ranking'!L74/3 -> 0.70366667 | F66: ='Percentile Ranking'!M74/3 + 'Percentile Ranking'!N74/3 + 'Percentile Ranking'!O74/3 -> 0.233 | G66: =C66 * 0.25 + D66 * 0.25 + E66 * 0.25 + F66 * 0.25 -> 0.57952083
B67: TECH MAHINDRA LTD | C67: ='Percentile Ranking'!C185/3+'Percentile Ranking'!D185/3+'Percentile Ranking'!E185/3 -> 0.29966667 | D67: ='Percentile Ranking'!F185*0.25+'Percentile Ranking'!G185*0.25+'Percentile Ranking'!H185*0.25+'Percentile Ranking'!I185*0.25 -> 0.75875 | E67: ='Percentile Ranking'!J185/3 + 'Percentile Ranking'!K185/3 + 'Percentile Ranking'!L185/3 -> 0.78066667 | F67: ='Percentile Ranking'!M185/3 + 'Percentile Ranking'!N185/3 + 'Percentile Ranking'!O185/3 -> 0.464 | G67: =C67 * 0.25 + D67 * 0.25 + E67 * 0.25 + F67 * 0.25 -> 0.57577083
B68: DABUR INDIA LTD | C68: ='Percentile Ranking'!C56/3+'Percentile Ranking'!D56/3+'Percentile Ranking'!E56/3 -> 0.298 | D68: ='Percentile Ranking'!F56*0.25+'Percentile Ranking'!G56*0.25+'Percentile Ranking'!H56*0.25+'Percentile Ranking'!I56*0.25 -> 0.805 | E68: ='Percentile Ranking'!J56/3 + 'Percentile Ranking'!K56/3 + 'Percentile Ranking'!L56/3 -> 0.71533333 | F68: ='Percentile Ranking'!M56/3 + 'Percentile Ranking'!N56/3 + 'Percentile Ranking'!O56/3 -> 0.45733333 | G68: =C68 * 0.25 + D68 * 0.25 + E68 * 0.25 + F68 * 0.25 -> 0.56891667
B69: SBI LIFE INSURANCE COMPANY LTD | C69: ='Percentile Ranking'!C163/3+'Percentile Ranking'!D163/3+'Percentile Ranking'!E163/3 -> 0.67866667 | D69: ='Percentile Ranking'!F163*0.25+'Percentile Ranking'!G163*0.25+'Percentile Ranking'!H163*0.25+'Percentile Ranking'!I163*0.25 -> 0.3945 | E69: ='Percentile Ranking'!J163/3 + 'Percentile Ranking'!K163/3 + 'Percentile Ranking'!L163/3 -> 0.93133333 | F69: ='Percentile Ranking'!M163/3 + 'Percentile Ranking'!N163/3 + 'Percentile Ranking'!O163/3 -> 0.268 | G69: =C69 * 0.25 + D69 * 0.25 + E69 * 0.25 + F69 * 0.25 -> 0.568125
B70: PB FINTECH LTD | C70: ='Percentile Ranking'!C148/3+'Percentile Ranking'!D148/3+'Percentile Ranking'!E148/3 -> 0.37833333 | D70: ='Percentile Ranking'!F148*0.25+'Percentile Ranking'!G148*0.25+'Percentile Ranking'!H148*0.25+'Percentile Ranking'!I148*0.25 -> 0.17975 | E70: ='Percentile Ranking'!J148/3 + 'Percentile Ranking'!K148/3 + 'Percentile Ranking'!L148/3 -> 0.93833333 | F70: ='Percentile Ranking'!M148/3 + 'Percentile Ranking'!N148/3 + 'Percentile Ranking'!O148/3 -> 0.764 | G70: =C70 * 0.25 + D70 * 0.25 + E70 * 0.25 + F70 * 0.25 -> 0.56510417
B71: HINDUSTAN PETROLEUM CORPORATION LTD | C71: ='Percentile Ranking'!C82/3+'Percentile Ranking'!D82/3+'Percentile Ranking'!E82/3 -> 0.42566667 | D71: ='Percentile Ranking'!F82*0.25+'Percentile Ranking'!G82*0.25+'Percentile Ranking'!H82*0.25+'Percentile Ranking'!I82*0.25 -> 0.623 | E71: ='Percentile Ranking'!J82/3 + 'Percentile Ranking'!K82/3 + 'Percentile Ranking'!L82/3 -> 0.35166667 | F71: ='Percentile Ranking'!M82/3 + 'Percentile Ranking'!N82/3 + 'Percentile Ranking'!O82/3 -> 0.85266667 | G71: =C71 * 0.25 + D71 * 0.25 + E71 * 0.25 + F71 * 0.25 -> 0.56325
B72: HINDUSTAN AERONAUTICS LTD | C72: ='Percentile Ranking'!C81/3+'Percentile Ranking'!D81/3+'Percentile Ranking'!E81/3 -> 0.573 | D72: ='Percentile Ranking'!F81*0.25+'Percentile Ranking'!G81*0.25+'Percentile Ranking'!H81*0.25+'Percentile Ranking'!I81*0.25 -> 0.6295 | E72: ='Percentile Ranking'!J81/3 + 'Percentile Ranking'!K81/3 + 'Percentile Ranking'!L81/3 -> 0.69666667 | F72: ='Percentile Ranking'!M81/3 + 'Percentile Ranking'!N81/3 + 'Percentile Ranking'!O81/3 -> 0.35033333 | G72: =C72 * 0.25 + D72 * 0.25 + E72 * 0.25 + F72 * 0.25 -> 0.562375
B73: LIFE INSURANCE CORPORATION OF INDIA | C73: ='Percentile Ranking'!C118/3+'Percentile Ranking'!D118/3+'Percentile Ranking'!E118/3 -> 0.04 | D73: ='Percentile Ranking'!F118*0.25+'Percentile Ranking'!G118*0.25+'Percentile Ranking'!H118*0.25+'Percentile Ranking'!I118*0.25 -> 0.56775 | E73: ='Percentile Ranking'!J118/3 + 'Percentile Ranking'!K118/3 + 'Percentile Ranking'!L118/3 -> 0.92966667 | F73: ='Percentile Ranking'!M118/3 + 'Percentile Ranking'!N118/3 + 'Percentile Ranking'!O118/3 -> 0.70866667 | G73: =C73 * 0.25 + D73 * 0.25 + E73 * 0.25 + F73 * 0.25 -> 0.56152083
B74: HYUNDAI MOTOR INDIA LTD | C74: ='Percentile Ranking'!C87/3+'Percentile Ranking'!D87/3+'Percentile Ranking'!E87/3 -> 0.04 | D74: ='Percentile Ranking'!F87*0.25+'Percentile Ranking'!G87*0.25+'Percentile Ranking'!H87*0.25+'Percentile Ranking'!I87*0.25 -> 0.89925 | E74: ='Percentile Ranking'!J87/3 + 'Percentile Ranking'!K87/3 + 'Percentile Ranking'!L87/3 -> 0.69033333 | F74: ='Percentile Ranking'!M87/3 + 'Percentile Ranking'!N87/3 + 'Percentile Ranking'!O87/3 -> 0.615 | G74: =C74 * 0.25 + D74 * 0.25 + E74 * 0.25 + F74 * 0.25 -> 0.56114583
B75: ZYDUS LIFESCIENCES LTD | C75: ='Percentile Ranking'!C204/3+'Percentile Ranking'!D204/3+'Percentile Ranking'!E204/3 -> 0.49933333 | D75: ='Percentile Ranking'!F204*0.25+'Percentile Ranking'!G204*0.25+'Percentile Ranking'!H204*0.25+'Percentile Ranking'!I204*0.25 -> 0.573 | E75: ='Percentile Ranking'!J204/3 + 'Percentile Ranking'!K204/3 + 'Percentile Ranking'!L204/3 -> 0.454 | F75: ='Percentile Ranking'!M204/3 + 'Percentile Ranking'!N204/3 + 'Percentile Ranking'!O204/3 -> 0.70666667 | G75: =C75 * 0.25 + D75 * 0.25 + E75 * 0.25 + F75 * 0.25 -> 0.55825
B76: MARICO LTD | C76: ='Percentile Ranking'!C125/3+'Percentile Ranking'!D125/3+'Percentile Ranking'!E125/3 -> 0.33333333 | D76: ='Percentile Ranking'!F125*0.25+'Percentile Ranking'!G125*0.25+'Percentile Ranking'!H125*0.25+'Percentile Ranking'!I125*0.25 -> 0.92225 | E76: ='Percentile Ranking'!J125/3 + 'Percentile Ranking'!K125/3 + 'Percentile Ranking'!L125/3 -> 0.74566667 | F76: ='Percentile Ranking'!M125/3 + 'Percentile Ranking'!N125/3 + 'Percentile Ranking'!O125/3 -> 0.22933333 | G76: =C76 * 0.25 + D76 * 0.25 + E76 * 0.25 + F76 * 0.25 -> 0.55764583
B77: BRITANNIA INDUSTRIES LTD | C77: ='Percentile Ranking'!C43/3+'Percentile Ranking'!D43/3+'Percentile Ranking'!E43/3 -> 0.48933333 | D77: ='Percentile Ranking'!F43*0.25+'Percentile Ranking'!G43*0.25+'Percentile Ranking'!H43*0.25+'Percentile Ranking'!I43*0.25 -> 0.96125 | E77: ='Percentile Ranking'!J43/3 + 'Percentile Ranking'!K43/3 + 'Percentile Ranking'!L43/3 -> 0.63833333 | F77: ='Percentile Ranking'!M43/3 + 'Percentile Ranking'!N43/3 + 'Percentile Ranking'!O43/3 -> 0.13733333 | G77: =C77 * 0.25 + D77 * 0.25 + E77 * 0.25 + F77 * 0.25 -> 0.5565625
B78: CUMMINS INDIA LTD | C78: ='Percentile Ranking'!C55/3+'Percentile Ranking'!D55/3+'Percentile Ranking'!E55/3 -> 0.46033333 | D78: ='Percentile Ranking'!F55*0.25+'Percentile Ranking'!G55*0.25+'Percentile Ranking'!H55*0.25+'Percentile Ranking'!I55*0.25 -> 0.79275 | E78: ='Percentile Ranking'!J55/3 + 'Percentile Ranking'!K55/3 + 'Percentile Ranking'!L55/3 -> 0.722 | F78: ='Percentile Ranking'!M55/3 + 'Percentile Ranking'!N55/3 + 'Percentile Ranking'!O55/3 -> 0.24966667 | G78: =C78 * 0.25 + D78 * 0.25 + E78 * 0.25 + F78 * 0.25 -> 0.5561875
B79: SONA BLW PRECISION FORGINGS LTD | C79: ='Percentile Ranking'!C169/3+'Percentile Ranking'!D169/3+'Percentile Ranking'!E169/3 -> 0.65333333 | D79: ='Percentile Ranking'!F169*0.25+'Percentile Ranking'!G169*0.25+'Percentile Ranking'!H169*0.25+'Percentile Ranking'!I169*0.25 -> 0.66825 | E79: ='Percentile Ranking'!J169/3 + 'Percentile Ranking'!K169/3 + 'Percentile Ranking'!L169/3 -> 0.516 | F79: ='Percentile Ranking'!M169/3 + 'Percentile Ranking'!N169/3 + 'Percentile Ranking'!O169/3 -> 0.37533333 | G79: =C79 * 0.25 + D79 * 0.25 + E79 * 0.25 + F79 * 0.25 -> 0.55322917
B80: ASHOK LEYLAND LTD | C80: ='Percentile Ranking'!C19/3+'Percentile Ranking'!D19/3+'Percentile Ranking'!E19/3 -> 0.53766667 | D80: ='Percentile Ranking'!F19*0.25+'Percentile Ranking'!G19*0.25+'Percentile Ranking'!H19*0.25+'Percentile Ranking'!I19*0.25 -> 0.57275 | E80: ='Percentile Ranking'!J19/3 + 'Percentile Ranking'!K19/3 + 'Percentile Ranking'!L19/3 -> 0.46733333 | F80: ='Percentile Ranking'!M19/3 + 'Percentile Ranking'!N19/3 + 'Percentile Ranking'!O19/3 -> 0.63333333 | G80: =C80 * 0.25 + D80 * 0.25 + E80 * 0.25 + F80 * 0.25 -> 0.55277083
B81: SIEMENS LTD | C81: ='Percentile Ranking'!C167/3+'Percentile Ranking'!D167/3+'Percentile Ranking'!E167/3 -> 0.44066667 | D81: ='Percentile Ranking'!F167*0.25+'Percentile Ranking'!G167*0.25+'Percentile Ranking'!H167*0.25+'Percentile Ranking'!I167*0.25 -> 0.682 | E81: ='Percentile Ranking'!J167/3 + 'Percentile Ranking'!K167/3 + 'Percentile Ranking'!L167/3 -> 0.772 | F81: ='Percentile Ranking'!M167/3 + 'Percentile Ranking'!N167/3 + 'Percentile Ranking'!O167/3 -> 0.30966667 | G81: =C81 * 0.25 + D81 * 0.25 + E81 * 0.25 + F81 * 0.25 -> 0.55108333
B82: TATA CONSUMER PRODUCTS LTD | C82: ='Percentile Ranking'!C179/3+'Percentile Ranking'!D179/3+'Percentile Ranking'!E179/3 -> 0.80233333 | D82: ='Percentile Ranking'!F179*0.25+'Percentile Ranking'!G179*0.25+'Percentile Ranking'!H179*0.25+'Percentile Ranking'!I179*0.25 -> 0.3845 | E82: ='Percentile Ranking'!J179/3 + 'Percentile Ranking'!K179/3 + 'Percentile Ranking'!L179/3 -> 0.71 | F82: ='Percentile Ranking'!M179/3 + 'Percentile Ranking'!N179/3 + 'Percentile Ranking'!O179/3 -> 0.29133333 | G82: =C82 * 0.25 + D82 * 0.25 + E82 * 0.25 + F82 * 0.25 -> 0.54704167
B83: SRF LTD | C83: ='Percentile Ranking'!C170/3+'Percentile Ranking'!D170/3+'Percentile Ranking'!E170/3 -> 0.623 | D83: ='Percentile Ranking'!F170*0.25+'Percentile Ranking'!G170*0.25+'Percentile Ranking'!H170*0.25+'Percentile Ranking'!I170*0.25 -> 0.5755 | E83: ='Percentile Ranking'!J170/3 + 'Percentile Ranking'!K170/3 + 'Percentile Ranking'!L170/3 -> 0.42533333 | F83: ='Percentile Ranking'!M170/3 + 'Percentile Ranking'!N170/3 + 'Percentile Ranking'!O170/3 -> 0.56133333 | G83: =C83 * 0.25 + D83 * 0.25 + E83 * 0.25 + F83 * 0.25 -> 0.54629167
B84: OBEROI REALTY LTD | C84: ='Percentile Ranking'!C140/3+'Percentile Ranking'!D140/3+'Percentile Ranking'!E140/3 -> 0.73033333 | D84: ='Percentile Ranking'!F140*0.25+'Percentile Ranking'!G140*0.25+'Percentile Ranking'!H140*0.25+'Percentile Ranking'!I140*0.25 -> 0.37175 | E84: ='Percentile Ranking'!J140/3 + 'Percentile Ranking'!K140/3 + 'Percentile Ranking'!L140/3 -> 0.57466667 | F84: ='Percentile Ranking'!M140/3 + 'Percentile Ranking'!N140/3 + 'Percentile Ranking'!O140/3 -> 0.50433333 | G84: =C84 * 0.25 + D84 * 0.25 + E84 * 0.25 + F84 * 0.25 -> 0.54527083
B85: SBI CARDS & PAYMENT SERVICES LTD | C85: ='Percentile Ranking'!C162/3+'Percentile Ranking'!D162/3+'Percentile Ranking'!E162/3 -> 0.881 | D85: ='Percentile Ranking'!F162*0.25+'Percentile Ranking'!G162*0.25+'Percentile Ranking'!H162*0.25+'Percentile Ranking'!I162*0.25 -> 0.46475 | E85: ='Percentile Ranking'!J162/3 + 'Percentile Ranking'!K162/3 + 'Percentile Ranking'!L162/3 -> 0.19266667 | F85: ='Percentile Ranking'!M162/3 + 'Percentile Ranking'!N162/3 + 'Percentile Ranking'!O162/3 -> 0.62633333 | G85: =C85 * 0.25 + D85 * 0.25 + E85 * 0.25 + F85 * 0.25 -> 0.5411875
B86: CG POWER & INDUSTRIAL SOLUTIONS LTD | C86: ='Percentile Ranking'!C46/3+'Percentile Ranking'!D46/3+'Percentile Ranking'!E46/3 -> 0.46033333 | D86: ='Percentile Ranking'!F46*0.25+'Percentile Ranking'!G46*0.25+'Percentile Ranking'!H46*0.25+'Percentile Ranking'!I46*0.25 -> 0.63675 | E86: ='Percentile Ranking'!J46/3 + 'Percentile Ranking'!K46/3 + 'Percentile Ranking'!L46/3 -> 0.67166667 | F86: ='Percentile Ranking'!M46/3 + 'Percentile Ranking'!N46/3 + 'Percentile Ranking'!O46/3 -> 0.387 | G86: =C86 * 0.25 + D86 * 0.25 + E86 * 0.25 + F86 * 0.25 -> 0.5389375
B87: HINDALCO INDUSTRIES LTD | C87: ='Percentile Ranking'!C80/3+'Percentile Ranking'!D80/3+'Percentile Ranking'!E80/3 -> 0.712 | D87: ='Percentile Ranking'!F80*0.25+'Percentile Ranking'!G80*0.25+'Percentile Ranking'!H80*0.25+'Percentile Ranking'!I80*0.25 -> 0.339 | E87: ='Percentile Ranking'!J80/3 + 'Percentile Ranking'!K80/3 + 'Percentile Ranking'!L80/3 -> 0.355 | F87: ='Percentile Ranking'!M80/3 + 'Percentile Ranking'!N80/3 + 'Percentile Ranking'!O80/3 -> 0.74033333 | G87: =C87 * 0.25 + D87 * 0.25 + E87 * 0.25 + F87 * 0.25 -> 0.53658333
B88: RAIL VIKAS NIGAM LTD | C88: ='Percentile Ranking'!C158/3+'Percentile Ranking'!D158/3+'Percentile Ranking'!E158/3 -> 0.78366667 | D88: ='Percentile Ranking'!F158*0.25+'Percentile Ranking'!G158*0.25+'Percentile Ranking'!H158*0.25+'Percentile Ranking'!I158*0.25 -> 0.58425 | E88: ='Percentile Ranking'!J158/3 + 'Percentile Ranking'!K158/3 + 'Percentile Ranking'!L158/3 -> 0.31633333 | F88: ='Percentile Ranking'!M158/3 + 'Percentile Ranking'!N158/3 + 'Percentile Ranking'!O158/3 -> 0.454 | G88: =C88 * 0.25 + D88 * 0.25 + E88 * 0.25 + F88 * 0.25 -> 0.5345625
B89: VOLTAS LTD | C89: ='Percentile Ranking'!C200/3+'Percentile Ranking'!D200/3+'Percentile Ranking'!E200/3 -> 0.489 | D89: ='Percentile Ranking'!F200*0.25+'Percentile Ranking'!G200*0.25+'Percentile Ranking'!H200*0.25+'Percentile Ranking'!I200*0.25 -> 0.618 | E89: ='Percentile Ranking'!J200/3 + 'Percentile Ranking'!K200/3 + 'Percentile Ranking'!L200/3 -> 0.72033333 | F89: ='Percentile Ranking'!M200/3 + 'Percentile Ranking'!N200/3 + 'Percentile Ranking'!O200/3 -> 0.30966667 | G89: =C89 * 0.25 + D89 * 0.25 + E89 * 0.25 + F89 * 0.25 -> 0.53425
B90: SIEMENS ENERGY INDIA LTD | C90: ='Percentile Ranking'!C166/3+'Percentile Ranking'!D166/3+'Percentile Ranking'!E166/3 -> 0.04 | D90: ='Percentile Ranking'!F166*0.25+'Percentile Ranking'!G166*0.25+'Percentile Ranking'!H166*0.25+'Percentile Ranking'!I166*0.25 -> 0.45225 | E90: ='Percentile Ranking'!J166/3 + 'Percentile Ranking'!K166/3 + 'Percentile Ranking'!L166/3 -> 0.73366667 | F90: ='Percentile Ranking'!M166/3 + 'Percentile Ranking'!N166/3 + 'Percentile Ranking'!O166/3 -> 0.90133333 | G90: =C90 * 0.25 + D90 * 0.25 + E90 * 0.25 + F90 * 0.25 -> 0.5318125
B91: SHREE CEMENT LTD | C91: ='Percentile Ranking'!C164/3+'Percentile Ranking'!D164/3+'Percentile Ranking'!E164/3 -> 0.49066667 | D91: ='Percentile Ranking'!F164*0.25+'Percentile Ranking'!G164*0.25+'Percentile Ranking'!H164*0.25+'Percentile Ranking'!I164*0.25 -> 0.49975 | E91: ='Percentile Ranking'!J164/3 + 'Percentile Ranking'!K164/3 + 'Percentile Ranking'!L164/3 -> 0.51766667 | F91: ='Percentile Ranking'!M164/3 + 'Percentile Ranking'!N164/3 + 'Percentile Ranking'!O164/3 -> 0.61633333 | G91: =C91 * 0.25 + D91 * 0.25 + E91 * 0.25 + F91 * 0.25 -> 0.53110417
B92: LUPIN LTD | C92: ='Percentile Ranking'!C121/3+'Percentile Ranking'!D121/3+'Percentile Ranking'!E121/3 -> 0.25966667 | D92: ='Percentile Ranking'!F121*0.25+'Percentile Ranking'!G121*0.25+'Percentile Ranking'!H121*0.25+'Percentile Ranking'!I121*0.25 -> 0.476 | E92: ='Percentile Ranking'!J121/3 + 'Percentile Ranking'!K121/3 + 'Percentile Ranking'!L121/3 -> 0.70366667 | F92: ='Percentile Ranking'!M121/3 + 'Percentile Ranking'!N121/3 + 'Percentile Ranking'!O121/3 -> 0.67833333 | G92: =C92 * 0.25 + D92 * 0.25 + E92 * 0.25 + F92 * 0.25 -> 0.52941667
B93: INDIAN OIL CORPORATION LTD | C93: ='Percentile Ranking'!C93/3+'Percentile Ranking'!D93/3+'Percentile Ranking'!E93/3 -> 0.335 | D93: ='Percentile Ranking'!F93*0.25+'Percentile Ranking'!G93*0.25+'Percentile Ranking'!H93*0.25+'Percentile Ranking'!I93*0.25 -> 0.58525 | E93: ='Percentile Ranking'!J93/3 + 'Percentile Ranking'!K93/3 + 'Percentile Ranking'!L93/3 -> 0.32333333 | F93: ='Percentile Ranking'!M93/3 + 'Percentile Ranking'!N93/3 + 'Percentile Ranking'!O93/3 -> 0.868 | G93: =C93 * 0.25 + D93 * 0.25 + E93 * 0.25 + F93 * 0.25 -> 0.52789583
B94: MUTHOOT FINANCE LTD | C94: ='Percentile Ranking'!C133/3+'Percentile Ranking'!D133/3+'Percentile Ranking'!E133/3 -> 0.74733333 | D94: ='Percentile Ranking'!F133*0.25+'Percentile Ranking'!G133*0.25+'Percentile Ranking'!H133*0.25+'Percentile Ranking'!I133*0.25 -> 0.47725 | E94: ='Percentile Ranking'!J133/3 + 'Percentile Ranking'!K133/3 + 'Percentile Ranking'!L133/3 -> 0.20266667 | F94: ='Percentile Ranking'!M133/3 + 'Percentile Ranking'!N133/3 + 'Percentile Ranking'!O133/3 -> 0.682 | G94: =C94 * 0.25 + D94 * 0.25 + E94 * 0.25 + F94 * 0.25 -> 0.5273125
B95: AMBUJA CEMENTS LTD | C95: ='Percentile Ranking'!C16/3+'Percentile Ranking'!D16/3+'Percentile Ranking'!E16/3 -> 0.47433333 | D95: ='Percentile Ranking'!F16*0.25+'Percentile Ranking'!G16*0.25+'Percentile Ranking'!H16*0.25+'Percentile Ranking'!I16*0.25 -> 0.3505 | E95: ='Percentile Ranking'!J16/3 + 'Percentile Ranking'!K16/3 + 'Percentile Ranking'!L16/3 -> 0.757 | F95: ='Percentile Ranking'!M16/3 + 'Percentile Ranking'!N16/3 + 'Percentile Ranking'!O16/3 -> 0.52266667 | G95: =C95 * 0.25 + D95 * 0.25 + E95 * 0.25 + F95 * 0.25 -> 0.526125
B96: ABB INDIA LTD | C96: ='Percentile Ranking'!C6/3+'Percentile Ranking'!D6/3+'Percentile Ranking'!E6/3 -> 0.53933333 | D96: ='Percentile Ranking'!F6*0.25+'Percentile Ranking'!G6*0.25+'Percentile Ranking'!H6*0.25+'Percentile Ranking'!I6*0.25 -> 0.642 | E96: ='Percentile Ranking'!J6/3 + 'Percentile Ranking'!K6/3 + 'Percentile Ranking'!L6/3 -> 0.72366667 | F96: ='Percentile Ranking'!M6/3 + 'Percentile Ranking'!N6/3 + 'Percentile Ranking'!O6/3 -> 0.19266667 | G96: =C96 * 0.25 + D96 * 0.25 + E96 * 0.25 + F96 * 0.25 -> 0.52441667
B97: BAJAJ FINSERV LTD | C97: ='Percentile Ranking'!C28/3+'Percentile Ranking'!D28/3+'Percentile Ranking'!E28/3 -> 0.938 | D97: ='Percentile Ranking'!F28*0.25+'Percentile Ranking'!G28*0.25+'Percentile Ranking'!H28*0.25+'Percentile Ranking'!I28*0.25 -> 0.46225 | E97: ='Percentile Ranking'!J28/3 + 'Percentile Ranking'!K28/3 + 'Percentile Ranking'!L28/3 -> 0.64666667 | F97: ='Percentile Ranking'!M28/3 + 'Percentile Ranking'!N28/3 + 'Percentile Ranking'!O28/3 -> 0.05 | G97: =C97 * 0.25 + D97 * 0.25 + E97 * 0.25 + F97 * 0.25 -> 0.52422917
B98: SHRIRAM FINANCE LTD | C98: ='Percentile Ranking'!C165/3+'Percentile Ranking'!D165/3+'Percentile Ranking'!E165/3 -> 0.83066667 | D98: ='Percentile Ranking'!F165*0.25+'Percentile Ranking'!G165*0.25+'Percentile Ranking'!H165*0.25+'Percentile Ranking'!I165*0.25 -> 0.338 | E98: ='Percentile Ranking'!J165/3 + 'Percentile Ranking'!K165/3 + 'Percentile Ranking'!L165/3 -> 0.15266667 | F98: ='Percentile Ranking'!M165/3 + 'Percentile Ranking'!N165/3 + 'Percentile Ranking'!O165/3 -> 0.772 | G98: =C98 * 0.25 + D98 * 0.25 + E98 * 0.25 + F98 * 0.25 -> 0.52333333
B99: GODREJ CONSUMER PRODUCTS LTD | C99: ='Percentile Ranking'!C71/3+'Percentile Ranking'!D71/3+'Percentile Ranking'!E71/3 -> 0.36866667 | D99: ='Percentile Ranking'!F71*0.25+'Percentile Ranking'!G71*0.25+'Percentile Ranking'!H71*0.25+'Percentile Ranking'!I71*0.25 -> 0.74125 | E99: ='Percentile Ranking'!J71/3 + 'Percentile Ranking'!K71/3 + 'Percentile Ranking'!L71/3 -> 0.69833333 | F99: ='Percentile Ranking'!M71/3 + 'Percentile Ranking'!N71/3 + 'Percentile Ranking'!O71/3 -> 0.27966667 | G99: =C99 * 0.25 + D99 * 0.25 + E99 * 0.25 + F99 * 0.25 -> 0.52197917
B100: GLENMARK PHARMACEUTICALS LTD | C100: ='Percentile Ranking'!C68/3+'Percentile Ranking'!D68/3+'Percentile Ranking'!E68/3 -> 0.246 | D100: ='Percentile Ranking'!F68*0.25+'Percentile Ranking'!G68*0.25+'Percentile Ranking'!H68*0.25+'Percentile Ranking'!I68*0.25 -> 0.569 | E100: ='Percentile Ranking'!J68/3 + 'Percentile Ranking'!K68/3 + 'Percentile Ranking'!L68/3 -> 0.49433333 | F100: ='Percentile Ranking'!M68/3 + 'Percentile Ranking'!N68/3 + 'Percentile Ranking'!O68/3 -> 0.767 | G100: =C100 * 0.25 + D100 * 0.25 + E100 * 0.25 + F100 * 0.25 -> 0.51908333
B101: ULTRATECH CEMENT LTD | C101: ='Percentile Ranking'!C192/3+'Percentile Ranking'!D192/3+'Percentile Ranking'!E192/3 -> 0.54966667 | D101: ='Percentile Ranking'!F192*0.25+'Percentile Ranking'!G192*0.25+'Percentile Ranking'!H192*0.25+'Percentile Ranking'!I192*0.25 -> 0.43825 | E101: ='Percentile Ranking'!J192/3 + 'Percentile Ranking'!K192/3 + 'Percentile Ranking'!L192/3 -> 0.43366667 | F101: ='Percentile Ranking'!M192/3 + 'Percentile Ranking'!N192/3 + 'Percentile Ranking'!O192/3 -> 0.655 | G101: =C101 * 0.25 + D101 * 0.25 + E101 * 0.25 + F101 * 0.25 -> 0.51914583
...

Sheet Master Data
B2: Master Sheet - Raw Data
C3: Growth Metrics (0.25) | F3: Return Metrics (0.25) | J3: Leverage Metrics (0.25) | M3: Valuation Metrics (0.25)
A4: # | B4: Company | C4: 10Y Sales CAGR | D4: 10Y EBITDA CAGR | E4: 10Y Net Profit CAGR | F4: 10Y Mean ROCE | G4: 10Y Mean ROE | H4: 10Y Mean ROA | I4: Asset Turnover Ratio - Current | J4: 10Y Debt to Equity Mean | K4: 10Y Debt to EBITDA Mean | L4: 10Y Interest Coverage Ratio Mean | M4: Current EV/EBITDA Ratio | N4: Current PEG Ratio | O4: Current P/B Ratio
B5: 360 ONE WAM LTD | C5: 0.058157681 | D5: 0.13129225 | E5: 0.12458284 | F5: 0.14439771 | G5: 0.14455584 | H5: 0.098759045 | I5: 0.21 | J5: 0.28651511 | K5: 0.46999193 | L5: 10.141703 | M5: 68.30523 | N5: -2.0132396 | O5: 6.7461712
B6: ABB INDIA LTD | C6: 0.041244246 | D6: 0.12149798 | E6: 0.20095707 | F6: 0.19998138 | G6: 0.14583465 | H6: 0.07307014 | I6: 1.04 | J6: 0.044920614 | K6: 0.29874474 | L6: 52.273781 | M6: 61.01149 | N6: 1.543865 | O6: 20.701385
B7: ACC LTD | C7: 0.063508927 | D7: 0.071871941 | E7: 0.15149665 | F7: 0.14758414 | G7: 0.11099816 | H7: 0.075660683 | I7: 0.89 | J7: 0.012001138 | K7: 0.068702999 | L7: 23.112222 | M7: 11.735329 | N7: 1.0643306 | O7: 1.9967767
B8: ADANI ENERGY SOLUTIONS LTD | C8: 0.21585966 | D8: -0.030365028 | E8: 0 | F8: 0.059354461 | G8: 0.0095197068 | H8: 0.0073652368 | I8: 0.36 | J8: 1.5560273 | K8: -672.65195 | L8: 1.3808395 | M8: 2295.9321 | N8: -47.403212 | O8: 5.3177615
B9: ADANI ENTERPRISES LTD | C9: 0.12709605 | D9: 0.24349411 | E9: 0.27789693 | F9: 0.16501569 | G9: 0.13172669 | H9: 0.044552174 | I9: 0.55 | J9: 0.87927813 | K9: 5.0673073 | L9: 3.6357609 | M9: 107.55819 | N9: 0.4031927 | O9: 10.011264
B10: ADANI GREEN ENERGY LTD | C10: 0 | D10: 0 | E10: 0 | F10: 0.04422918 | G10: 0.0048191002 | H10: -0.00083313028 | I10: 0.11 | J10: 2.5106129 | K10: 41.543312 | L10: 0.91005016 | M10: 110.47046 | N10: 11.615886 | O10: 18.298363
B11: ADANI PORTS & SPECIAL ECONOMIC ZONE LTD | C11: 0.055273524 | D11: 0.04847162 | E11: -0.018595553 | F11: 0.087839686 | G11: 0.084746588 | H11: 0.034349637 | I11: 0.24 | J11: 1.468425 | K11: 10.186668 | L11: 2.2834278 | M11: 57.565439 | N11: 2.5149985 | O11: 8.4416426
B12: ADANI POWER LTD | C12: 0.14594229 | D12: 0.18677756 | E12: 0.61370628 | F12: 0.10356108 | G12: -0.0054888925 | H12: 0.035233391 | I12: 0.55 | J12: 1.4721055 | K12: -93.983633 | L12: 2.1441064 | M12: 11.6182 | N12: -0.41327703 | O12: 4.229028
B13: ADANI TOTAL GAS LTD | C13: 0.16016358 | D13: 0.18529723 | E13: 0.23040591 | F13: 0.21608012 | G13: 0.19670399 | H13: 0.10510485 | I13: 0.7 | J13: 0.53076887 | K13: 1.5530747 | L13: 9.5618114 | M13: 59.492747 | N13: -131.48324 | O13: 15.835615
B14: ADITYA BIRLA CAPITAL LTD | C14: 1.1492571 | D14: 1.5005678 | E14: 0 | F14: 0.030366537 | G14: 0.034976949 | H14: 0.012094898 | I14: 0.16 | J14: 1.0027578 | K14: 15.902936 | L14: 738.66487 | M14: 13.163099 | N14: 33.891663 | O14: 1.9150765
B15: ALKEM LABORATORIES LTD | C15: 0.084644805 | D15: 0.11422071 | E15: 0.12535318 | F15: 0.17768673 | G15: 0.17383134 | H15: 0.12628916 | I15: 0.78 | J15: 0.13127626 | K15: 0.64724874 | L15: 33.873361 | M15: 26.791453 | N15: 0.83791192 | O15: 4.7383491
B16: AMBUJA CEMENTS LTD | C16: 0.075248702 | D16: 0.066522698 | E16: 0.16611917 | F16: 0.093788068 | G16: 0.073575396 | H16: 0.060028116 | I16: 0.48 | J16: 0.010924864 | K16: 0.10218137 | L16: 24.957476 | M16: 43.413516 | N16: 0.81175009 | O16: 2.7280982
... B204: ZYDUS LIFESCIENCES LTD | C204: 0.079534843 | D204: 0.11616935 | E204: 0.10979991 | F204: 0.14280256 | G204: 0.14710412 | H204: 0.096432496 | I204: 0.71 | J204: 0.3567481 | K204: 2.588669 | L204: 20.421517 | M204: 12.588404 | N204: 0.2277866 | O204: 4.2090206

Sheet Percentile Ranking
B2: Percentile Score
C3: Growth Metrics (0.25) | F3: Return Metrics (0.25) | J3: Leverage Metrics (0.25) | M3: Valuation Metrics (0.25)
A4: # | B4: Company | C4: 10Y Sales CAGR | D4: 10Y EBITDA CAGR | E4: 10Y Net Profit CAGR | F4: 10Y Mean ROCE | G4: 10Y Mean ROE | H4: 10Y Mean ROA | I4: Asset Turnover Ratio - Current | J4: 10Y Debt to Equity Mean | K4: 10Y Debt to EBITDA Mean | L4: 10Y Interest Coverage Ratio Mean | M4: Current EV/EBITDA Ratio | N4: Current PEG Ratio | O4: Current P/B Ratio
B5: 360 ONE WAM LTD | C5: =IFERROR(_xlfn.PERCENTRANK.INC('Master Data'!$C$5:$C$204,'Master Data'!$C5),0) -> 0.276 | D5: =IFERROR(_xlfn.PERCENTRANK.INC('Master Data'!$D$5:$D$204,'Master Data'!$D5),0) -> 0.648 | E5: =IFERROR(_xlfn.PERCENTRANK.INC('Master Data'!$E$5:$E$204,'Master Data'!$E5),0) -> 0.578 | F5: =IFERROR(_xlfn.PERCENTRANK.INC('Master Data'!$F$5:$F$204,'Master Data'!$F5),0) -> 0.513 | G5: =IFERROR(_xlfn.PERCENTRANK.INC('Master Data'!$G$5:$G$204,'Master Data'!$G5),0) -> 0.548 | H5: =IFERROR(_xlfn.PERCENTRANK.INC('Master Data'!$H$5:$H$204,'Master Data'!$H5),0) -> 0.704 | I5: =IFERROR(_xlfn.PERCENTRANK.INC('Master Data'!$I$5:$I$204,'Master Data'!$I5),0) -> 0.226 | J5: =IFERROR(1-_xlfn.PERCENTRANK.INC('Master Data'!$J$5:$J$204,'Master Data'!$J5),0) -> 0.472 | K5: =IFERROR(1-_xlfn.PERCENTRANK.INC('Master Data'!$K$5:$K$204,'Master Data'!$K5),0) -> 0.613 | L5: =IFERROR(_xlfn.PERCENTRANK.INC('Master Data'!$L$5:$L$204,'Master Data'!$L5),0) -> 0.477 | M5: =IFERROR(1-_xlfn.PERCENTRANK.INC('Master Data'!$M$5:$M$204,'Master Data'!$M5),0) -> 0.151 | N5: =IFERROR(1-_xlfn.PERCENTRANK.INC('Master Data'!$N$5:$N$204,'Master Data'!$N5),0) -> 0.834 | O5: =IFERROR(1-_xlfn.PERCENTRANK.INC('Master Data'!$O$5:$O$204,'Master Data'!$O5),0) -> 0.417
B6: ABB INDIA LTD | C6: =IFERROR(_xlfn.PERCENTRANK.INC('Master Data'!$C$5:$C$204,'Master Data'!$C6),0) -> 0.211 | D6: =IFERROR(_xlfn.PERCENTRANK.INC('Master Data'!$D$5:$D$204,'Master Data'!$D6),0) -> 0.608 | E6: =IFERROR(_xlfn.PERCENTRANK.INC('Master Data'!$E$5:$E$204,'Master Data'!$E6),0) -> 0.799 | F6: =IFERROR(_xlfn.PERCENTRANK.INC('Master Data'!$F$5:$F$204,'Master Data'!$F6),0) -> 0.698 | G6: =IFERROR(_xlfn.PERCENTRANK.INC('Master Data'!$G$5:$G$204,'Master Data'!$G6),0) -> 0.553 | H6: =IFERROR(_xlfn.PERCENTRANK.INC('Master Data'!$H$5:$H$204,'Master Data'!$H6),0) -> 0.573 | I6: =IFERROR(_xlfn.PERCENTRANK.INC('Master Data'!$I$5:$I$204,'Master Data'!$I6),0) -> 0.744 | J6: =IFERROR(1-_xlfn.PERCENTRANK.INC('Master Data'!$J$5:$J$204,'Master Data'!$J6),0) -> 0.789 | K6: =IFERROR(1-_xlfn.PERCENTRANK.INC('Master Data'!$K$5:$K$204,'Master Data'!$K6),0) -> 0.668 | L6: =IFERROR(_xlfn.PERCENTRANK.INC('Master Data'!$L$5:$L$204,'Master Data'!$L6),0) -> 0.714 | M6: =IFERROR(1-_xlfn.PERCENTRANK.INC('Master Data'!$M$5:$M$204,'Master Data'!$M6),0) -> 0.181 | N6: =IFERROR(1-_xlfn.PERCENTRANK.INC('Master Data'!$N$5:$N$204,'Master Data'!$N6),0) -> 0.337 | O6: =IFERROR(1-_xlfn.PERCENTRANK.INC('Master Data'!$O$5:$O$204,'Master Data'!$O6),0) -> 0.06
B7: ACC LTD | C7: =IFERROR(_xlfn.PERCENTRANK.INC('Master Data'!$C$5:$C$204,'Master Data'!$C7),0) -> 0.302 | D7: =IFERROR(_xlfn.PERCENTRANK.INC('Master Data'!$D$5:$D$204,'Master Data'!$D7),0) -> 0.362 | E7: =IFERROR(_xlfn.PERCENTRANK.INC('Master Data'!$E$5:$E$204,'Master Data'!$E7),0) -> 0.698 | F7: =IFERROR(_xlfn.PERCENTRANK.INC('Master Data'!$F$5:$F$204,'Master Data'!$F7),0) -> 0.533 | G7: =IFERROR(_xlfn.PERCENTRANK.INC('Master Data'!$G$5:$G$204,'Master Data'!$G7),0) -> 0.347 | H7: =IFERROR(_xlfn.PERCENTRANK.INC('Master Data'!$H$5:$H$204,'Master Data'!$H7),0) -> 0.593 | I7: =IFERROR(_xlfn.PERCENTRANK.INC('Master Data'!$I$5:$I$204,'Master Data'!$I7),0) -> 0.663 | J7: =IFERROR(1-_xlfn.PERCENTRANK.INC('Master Data'!$J$5:$J$204,'Master Data'!$J7),0) -> 0.869 | K7: =IFERROR(1-_xlfn.PERCENTRANK.INC('Master Data'!$K$5:$K$204,'Master Data'!$K7),0) -> 0.814 | L7: =IFERROR(_xlfn.PERCENTRANK.INC('Master Data'!$L$5:$L$204,'Master Data'!$L7),0) -> 0.588 | M7: =IFERROR(1-_xlfn.PERCENTRANK.INC('Master Data'!$M$5:$M$204,'Master Data'!$M7),0) -> 0.864 | N7: =IFERROR(1-_xlfn.PERCENTRANK.INC('Master Data'!$N$5:$N$204,'Master Data'!$N7),0) -> 0.427 | O7: =IFERROR(1-_xlfn.PERCENTRANK.INC('Master Data'!$O$5:$O$204,'Master Data'!$O7),0) -> 0.834
B8: ADANI ENERGY SOLUTIONS LTD | C8: =IFERROR(_xlfn.PERCENTRANK.INC('Master Data'!$C$5:$C$204,'Master Data'!$C8),0) -> 0.93 | D8: =IFERROR(_xlfn.PERCENTRANK.INC('Master Data'!$D$5:$D$204,'Master Data'!$D8),0) -> 0.02 | E8: =IFERROR(_xlfn.PERCENTRANK.INC('Master Data'!$E$5:$E$204,'Master Data'!$E8),0) -> 0.04 | F8: =IFERROR(_xlfn.PERCENTRANK.INC('Master Data'!$F$5:$F$204,'Master Data'!$F8),0) -> 0.176 | G8: =IFERROR(_xlfn.PERCENTRANK.INC('Master Data'!$G$5:$G$204,'Master Data'!$G8),0) -> 0.08 | H8: =IFERROR(_xlfn.PERCENTRANK.INC('Master Data'!$H$5:$H$204,'Master Data'!$H8),0) -> 0.121 | I8: =IFERROR(_xlfn.PERCENTRANK.INC('Master Data'!$I$5:$I$204,'Master Data'!$I8),0) -> 0.327 | J8: =IFERROR(1-_xlfn.PERCENTRANK.INC('Master Data'!$J$5:$J$204,'Master Data'!$J8),0) -> 0.186 | K8: =IFERROR(1-_xlfn.PERCENTRANK.INC('Master Data'!$K$5:$K$204,'Master Data'!$K8),0) -> 1 | L8: =IFERROR(_xlfn.PERCENTRANK.INC('Master Data'!$L$5:$L$204,'Master Data'!$L8),0) -> 0.111 | M8: =IFERROR(1-_xlfn.PERCENTRANK.INC('Master Data'!$M$5:$M$204,'Master Data'!$M8),0) -> 0 | N8: =IFERROR(1-_xlfn.PERCENTRANK.INC('Master Data'!$N$5:$N$204,'Master Data'!$N8),0) -> 0.99 | O8: =IFERROR(1-_xlfn.PERCENTRANK.INC('Master Data'!$O$5:$O$204,'Master Data'!$O8),0) -> 0.528
B9: ADANI ENTERPRISES LTD | C9: =IFERROR(_xlfn.PERCENTRANK.INC('Master Data'!$C$5:$C$204,'Master Data'!$C9),0) -> 0.698 | D9: =IFERROR(_xlfn.PERCENTRANK.INC('Master Data'!$D$5:$D$204,'Master Data'!$D9),0) -> 0.945 | E9: =IFERROR(_xlfn.PERCENTRANK.INC('Master Data'!$E$5:$E$204,'Master Data'!$E9),0) -> 0.93 | F9: =IFERROR(_xlfn.PERCENTRANK.INC('Master Data'!$F$5:$F$204,'Master Data'!$F9),0) -> 0.578 | G9: =IFERROR(_xlfn.PERCENTRANK.INC('Master Data'!$G$5:$G$204,'Master Data'!$G9),0) -> 0.467 | H9: =IFERROR(_xlfn.PERCENTRANK.INC('Master Data'!$H$5:$H$204,'Master Data'!$H9),0) -> 0.397 | I9: =IFERROR(_xlfn.PERCENTRANK.INC('Master Data'!$I$5:$I$204,'Master Data'!$I9),0) -> 0.407 | J9: =IFERROR(1-_xlfn.PERCENTRANK.INC('Master Data'!$J$5:$J$204,'Master Data'!$J9),0) -> 0.266 | K9: =IFERROR(1-_xlfn.PERCENTRANK.INC('Master Data'!$K$5:$K$204,'Master Data'!$K9),0) -> 0.241 | L9: =IFERROR(_xlfn.PERCENTRANK.INC('Master Data'!$L$5:$L$204,'Master Data'!$L9),0) -> 0.307 | M9: =IFERROR(1-_xlfn.PERCENTRANK.INC('Master Data'!$M$5:$M$204,'Master Data'!$M9),0) -> 0.09 | N9: =IFERROR(1-_xlfn.PERCENTRANK.INC('Master Data'!$N$5:$N$204,'Master Data'!$N9),0) -> 0.598 | O9: =IFERROR(1-_xlfn.PERCENTRANK.INC('Master Data'!$O$5:$O$204,'Master Data'!$O9),0) -> 0.281
B10: ADANI GREEN ENERGY LTD | C10: =IFERROR(_xlfn.PERCENTRANK.INC('Master Data'!$C$5:$C$204,'Master Data'!$C10),0) -> 0.03 | D10: =IFERROR(_xlfn.PERCENTRANK.INC('Master Data'!$D$5:$D$204,'Master Data'!$D10),0) -> 0.05 | E10: =IFERROR(_xlfn.PERCENTRANK.INC('Master Data'!$E$5:$E$204,'Master Data'!$E10),0) -> 0.04 | F10: =IFERROR(_xlfn.PERCENTRANK.INC('Master Data'!$F$5:$F$204,'Master Data'!$F10),0) -> 0.075 | G10: =IFERROR(_xlfn.PERCENTRANK.INC('Master Data'!$G$5:$G$204,'Master Data'!$G10),0) -> 0.065 | H10: =IFERROR(_xlfn.PERCENTRANK.INC('Master Data'!$H$5:$H$204,'Master Data'!$H10),0) -> 0.05 | I10: =IFERROR(_xlfn.PERCENTRANK.INC('Master Data'!$I$5:$I$204,'Master Data'!$I10),0) -> 0.131 | J10: =IFERROR(1-_xlfn.PERCENTRANK.INC('Master Data'!$J$5:$J$204,'Master Data'!$J10),0) -> 0.156 | K10: =IFERROR(1-_xlfn.PERCENTRANK.INC('Master Data'!$K$5:$K$204,'Master Data'!$K10),0) -> 0.015 | L10: =IFERROR(_xlfn.PERCENTRANK.INC('Master Data'!$L$5:$L$204,'Master Data'!$L10),0) -> 0.04 | M10: =IFERROR(1-_xlfn.PERCENTRANK.INC('Master Data'!$M$5:$M$204,'Master Data'!$M10),0) -> 0.085 | N10: =IFERROR(1-_xlfn.PERCENTRANK.INC('Master Data'!$N$5:$N$204,'Master Data'!$N10),0) -> 0.05 | O10: =IFERROR(1-_xlfn.PERCENTRANK.INC('Master Data'!$O$5:$O$204,'Master Data'!$O10),0) -> 0.08
B11: ADANI PORTS & SPECIAL ECONOMIC ZONE LTD | C11: =IFERROR(_xlfn.PERCENTRANK.INC('Master Data'!$C$5:$C$204,'Master Data'!$C11),0) -> 0.261 | D11: =IFERROR(_xlfn.PERCENTRANK.INC('Master Data'!$D$5:$D$204,'Master Data'!$D11),0) -> 0.302 | E11: =IFERROR(_xlfn.PERCENTRANK.INC('Master Data'!$E$5:$E$204,'Master Data'!$E11),0) -> 0.025 | F11: =IFERROR(_xlfn.PERCENTRANK.INC('Master Data'!$F$5:$F$204,'Master Data'!$F11),0) -> 0.307 | G11: =IFERROR(_xlfn.PERCENTRANK.INC('Master Data'!$G$5:$G$204,'Master Data'!$G11),0) -> 0.256 | H11: =IFERROR(_xlfn.PERCENTRANK.INC('Master Data'!$H$5:$H$204,'Master Data'!$H11),0) -> 0.322 | I11: =IFERROR(_xlfn.PERCENTRANK.INC('Master Data'!$I$5:$I$204,'Master Data'!$I11),0) -> 0.246 | J11: =IFERROR(1-_xlfn.PERCENTRANK.INC('Master Data'!$J$5:$J$204,'Master Data'!$J11),0) -> 0.196 | K11: =IFERROR(1-_xlfn.PERCENTRANK.INC('Master Data'!$K$5:$K$204,'Master Data'!$K11),0) -> 0.141 | L11: =IFERROR(_xlfn.PERCENTRANK.INC('Master Data'!$L$5:$L$204,'Master Data'!$L11),0) -> 0.236 | M11: =IFERROR(1-_xlfn.PERCENTRANK.INC('Master Data'!$M$5:$M$204,'Master Data'!$M11),0) -> 0.211 | N11: =IFERROR(1-_xlfn.PERCENTRANK.INC('Master Data'!$N$5:$N$204,'Master Data'!$N11),0) -> 0.236 | O11: =IFERROR(1-_xlfn.PERCENTRANK.INC('Master Data'!$O$5:$O$204,'Master Data'!$O11),0) -> 0.342
B12: ADANI POWER LTD | C12: =IFERROR(_xlfn.PERCENTRANK.INC('Master Data'!$C$5:$C$204,'Master Data'!$C12),0) -> 0.794 | D12: =IFERROR(_xlfn.PERCENTRANK.INC('Master Data'!$D$5:$D$204,'Master Data'!$D12),0) -> 0.844 | E12: =IFERROR(_xlfn.PERCENTRANK.INC('Master Data'!$E$5:$E$204,'Master Data'!$E12),0) -> 1 | F12: =IFERROR(_xlfn.PERCENTRANK.INC('Master Data'!$F$5:$F$204,'Master Data'!$F12),0) -> 0.352 | G12: =IFERROR(_xlfn.PERCENTRANK.INC('Master Data'!$G$5:$G$204,'Master Data'!$G12),0) -> 0.05 | H12: =IFERROR(_xlfn.PERCENTRANK.INC('Master Data'!$H$5:$H$204,'Master Data'!$H12),0) -> 0.332 | I12: =IFERROR(_xlfn.PERCENTRANK.INC('Master Data'!$I$5:$I$204,'Master Data'!$I12),0) -> 0.407 | J12: =IFERROR(1-_xlfn.PERCENTRANK.INC('Master Data'!$J$5:$J$204,'Master Data'!$J12),0) -> 0.191 | K12: =IFERROR(1-_xlfn.PERCENTRANK.INC('Master Data'!$K$5:$K$204,'Master Data'!$K12),0) -> 0.995 | L12: =IFERROR(_xlfn.PERCENTRANK.INC('Master Data'!$L$5:$L$204,'Master Data'!$L12),0) -> 0.216 | M12: =IFERROR(1-_xlfn.PERCENTRANK.INC('Master Data'!$M$5:$M$204,'Master Data'!$M12),0) -> 0.874 | N12: =IFERROR(1-_xlfn.PERCENTRANK.INC('Master Data'!$N$5:$N$204,'Master Data'!$N12),0) -> 0.769 | O12: =IFERROR(1-_xlfn.PERCENTRANK.INC('Master Data'!$O$5:$O$204,'Master Data'!$O12),0) -> 0.623
B13: ADANI TOTAL GAS LTD | C13: =IFERROR(_xlfn.PERCENTRANK.INC('Master Data'!$C$5:$C$204,'Master Data'!$C13),0) -> 0.859 | D13: =IFERROR(_xlfn.PERCENTRANK.INC('Master Data'!$D$5:$D$204,'Master Data'!$D13),0) -> 0.829 | E13: =IFERROR(_xlfn.PERCENTRANK.INC('Master Data'!$E$5:$E$204,'Master Data'!$E13),0) -> 0.869 | F13: =IFERROR(_xlfn.PERCENTRANK.INC('Master Data'!$F$5:$F$204,'Master Data'!$F13),0) -> 0.719 | G13: =IFERROR(_xlfn.PERCENTRANK.INC('Master Data'!$G$5:$G$204,'Master Data'!$G13),0) -> 0.779 | H13: =IFERROR(_xlfn.PERCENTRANK.INC('Master Data'!$H$5:$H$204,'Master Data'!$H13),0) -> 0.744 | I13: =IFERROR(_xlfn.PERCENTRANK.INC('Master Data'!$I$5:$I$204,'Master Data'!$I13),0) -> 0.513 | J13: =IFERROR(1-_xlfn.PERCENTRANK.INC('Master Data'!$J$5:$J$204,'Master Data'!$J13),0) -> 0.357 | K13: =IFERROR(1-_xlfn.PERCENTRANK.INC('Master Data'!$K$5:$K$204,'Master Data'!$K13),0) -> 0.452 | L13: =IFERROR(_xlfn.PERCENTRANK.INC('Master Data'!$L$5:$L$204,'Master Data'!$L13),0) -> 0.462 | M13: =IFERROR(1-_xlfn.PERCENTRANK.INC('Master Data'!$M$5:$M$204,'Master Data'!$M13),0) -> 0.191 | N13: =IFERROR(1-_xlfn.PERCENTRANK.INC('Master Data'!$N$5:$N$204,'Master Data'!$N13),0) -> 1 | O13: =IFERROR(1-_xlfn.PERCENTRANK.INC('Master Data'!$O$5:$O$204,'Master Data'!$O13),0) -> 0.116
B14: ADITYA BIRLA CAPITAL LTD | C14: =IFERROR(_xlfn.PERCENTRANK.INC('Master Data'!$C$5:$C$204,'Master Data'!$C14),0) -> 1 | D14: =IFERROR(_xlfn.PERCENTRANK.INC('Master Data'!$D$5:$D$204,'Master Data'!$D14),0) -> 1 | E14: =IFERROR(_xlfn.PERCENTRANK.INC('Master Data'!$E$5:$E$204,'Master Data'!$E14),0) -> 0.04 | F14: =IFERROR(_xlfn.PERCENTRANK.INC('Master Data'!$F$5:$F$204,'Master Data'!$F14),0) -> 0.055 | G14: =IFERROR(_xlfn.PERCENTRANK.INC('Master Data'!$G$5:$G$204,'Master Data'!$G14),0) -> 0.116 | H14: =IFERROR(_xlfn.PERCENTRANK.INC('Master Data'!$H$5:$H$204,'Master Data'!$H14),0) -> 0.156 | I14: =IFERROR(_xlfn.PERCENTRANK.INC('Master Data'!$I$5:$I$204,'Master Data'!$I14),0) -> 0.186 | J14: =IFERROR(1-_xlfn.PERCENTRANK.INC('Master Data'!$J$5:$J$204,'Master Data'!$J14),0) -> 0.236 | K14: =IFERROR(1-_xlfn.PERCENTRANK.INC('Master Data'!$K$5:$K$204,'Master Data'!$K14),0) -> 0.095 | L14: =IFERROR(_xlfn.PERCENTRANK.INC('Master Data'!$L$5:$L$204,'Master Data'!$L14),0) -> 0.965 | M14: =IFERROR(1-_xlfn.PERCENTRANK.INC('Master Data'!$M$5:$M$204,'Master Data'!$M14),0) -> 0.814 | N14: =IFERROR(1-_xlfn.PERCENTRANK.INC('Master Data'!$N$5:$N$204,'Master Data'!$N14),0) -> 0.015 | O14: =IFERROR(1-_xlfn.PERCENTRANK.INC('Master Data'!$O$5:$O$204,'Master Data'!$O14),0) -> 0.844
B15: ALKEM LABORATORIES LTD | C15: =IFERROR(_xlfn.PERCENTRANK.INC('Master Data'!$C$5:$C$204,'Master Data'!$C15),0) -> 0.447 | D15: =IFERROR(_xlfn.PERCENTRANK.INC('Master Data'!$D$5:$D$204,'Master Data'!$D15),0) -> 0.568 | E15: =IFERROR(_xlfn.PERCENTRANK.INC('Master Data'!$E$5:$E$204,'Master Data'!$E15),0) -> 0.583 | F15: =IFERROR(_xlfn.PERCENTRANK.INC('Master Data'!$F$5:$F$204,'Master Data'!$F15),0) -> 0.623 | G15: =IFERROR(_xlfn.PERCENTRANK.INC('Master Data'!$G$5:$G$204,'Master Data'!$G15),0) -> 0.683 | H15: =IFERROR(_xlfn.PERCENTRANK.INC('Master Data'!$H$5:$H$204,'Master Data'!$H15),0) -> 0.809 | I15: =IFERROR(_xlfn.PERCENTRANK.INC('Master Data'!$I$5:$I$204,'Master Data'!$I15),0) -> 0.578 | J15: =IFERROR(1-_xlfn.PERCENTRANK.INC('Master Data'!$J$5:$J$204,'Master Data'!$J15),0) -> 0.588 | K15: =IFERROR(1-_xlfn.PERCENTRANK.INC('Master Data'!$K$5:$K$204,'Master Data'!$K15),0) -> 0.548 | L15: =IFERROR(_xlfn.PERCENTRANK.INC('Master Data'!$L$5:$L$204,'Master Data'!$L15),0) -> 0.658 | M15: =IFERROR(1-_xlfn.PERCENTRANK.INC('Master Data'!$M$5:$M$204,'Master Data'!$M15),0) -> 0.497 | N15: =IFERROR(1-_xlfn.PERCENTRANK.INC('Master Data'!$N$5:$N$204,'Master Data'!$N15),0) -> 0.467 | O15: =IFERROR(1-_xlfn.PERCENTRANK.INC('Master Data'!$O$5:$O$204,'Master Data'!$O15),0) -> 0.583
B16: AMBUJA CEMENTS LTD | C16: =IFERROR(_xlfn.PERCENTRANK.INC('Master Data'!$C$5:$C$204,'Master Data'!$C16),0) -> 0.367 | D16: =IFERROR(_xlfn.PERCENTRANK.INC('Master Data'!$D$5:$D$204,'Master Data'!$D16),0) -> 0.337 | E16: =IFERROR(_xlfn.PERCENTRANK.INC('Master Data'!$E$5:$E$204,'Master Data'!$E16),0) -> 0.719 | F16: =IFERROR(_xlfn.PERCENTRANK.INC('Master Data'!$F$5:$F$204,'Master Data'!$F16),0) -> 0.327 | G16: =IFERROR(_xlfn.PERCENTRANK.INC('Master Data'!$G$5:$G$204,'Master Data'!$G16),0) -> 0.221 | H16: =IFERROR(_xlfn.PERCENTRANK.INC('Master Data'!$H$5:$H$204,'Master Data'!$H16),0) -> 0.482 | I16: =IFERROR(_xlfn.PERCENTRANK.INC('Master Data'!$I$5:$I$204,'Master Data'!$I16),0) -> 0.372 | J16: =IFERROR(1-_xlfn.PERCENTRANK.INC('Master Data'!$J$5:$J$204,'Master Data'!$J16),0) -> 0.884 | K16: =IFERROR(1-_xlfn.PERCENTRANK.INC('Master Data'!$K$5:$K$204,'Master Data'!$K16),0) -> 0.784 | L16: =IFERROR(_xlfn.PERCENTRANK.INC('Master Data'!$L$5:$L$204,'Master Data'!$L16),0) -> 0.603 | M16: =IFERROR(1-_xlfn.PERCENTRANK.INC('Master Data'!$M$5:$M$204,'Master Data'!$M16),0) -> 0.322 | N16: =IFERROR(1-_xlfn.PERCENTRANK.INC('Master Data'!$N$5:$N$204,'Master Data'!$N16),0) -> 0.472 | O16: =IFERROR(1-_xlfn.PERCENTRANK.INC('Master Data'!$O$5:$O$204,'Master Data'!$O16),0) -> 0.774
... B204: ZYDUS LIFESCIENCES LTD | C204: =IFERROR(_xlfn.PERCENTRANK.INC('Master Data'!$C$5:$C$204,'Master Data'!$C204),0) -> 0.387 | D204: =IFERROR(_xlfn.PERCENTRANK.INC('Master Data'!$D$5:$D$204,'Master Data'!$D204),0) -> 0.573 | E204: =IFERROR(_xlfn.PERCENTRANK.INC('Master Data'!$E$5:$E$204,'Master Data'!$E204),0) -> 0.538 | F204: =IFERROR(_xlfn.PERCENTRANK.INC('Master Data'!$F$5:$F$204,'Master Data'!$F204),0) -> 0.503 | G204: =IFERROR(_xlfn.PERCENTRANK.INC('Master Data'!$G$5:$G$204,'Master Data'!$G204),0) -> 0.563 | H204: =IFERROR(_xlfn.PERCENTRANK.INC('Master Data'!$H$5:$H$204,'Master Data'!$H204),0) -> 0.698 | I204: =IFERROR(_xlfn.PERCENTRANK.INC('Master Data'!$I$5:$I$204,'Master Data'!$I204),0) -> 0.528 | J204: =IFERROR(1-_xlfn.PERCENTRANK.INC('Master Data'!$J$5:$J$204,'Master Data'!$J204),0) -> 0.437 | K204: =IFERROR(1-_xlfn.PERCENTRANK.INC('Master Data'!$K$5:$K$204,'Master Data'!$K204),0) -> 0.352 | L204: =IFERROR(_xlfn.PERCENTRANK.INC('Master Data'!$L$5:$L$204,'Master Data'!$L204),0) -> 0.573 | M204: =IFERROR(1-_xlfn.PERCENTRANK.INC('Master Data'!$M$5:$M$204,'Master Data'!$M204),0) -> 0.839 | N204: =IFERROR(1-_xlfn.PERCENTRANK.INC('Master Data'!$N$5:$N$204,'Master Data'!$N204),0) -> 0.648 | O204: =IFERROR(1-_xlfn.PERCENTRANK.INC('Master Data'!$O$5:$O$204,'Master Data'!$O204),0) -> 0.633
